{"records":[{"emblem":"<img src='https:\/\/github.com\/GalconElim\/elim_rankings\/raw\/master\/rank10.png' width=49 height=49 style='margin-top:-100%;margin-bottom:-100%;'\/>", "rating":1264, "alias":"rickss", "ratingdelta":-3, "rank":1, "activity":237, "score":2222}, {"emblem":"<img src='https:\/\/github.com\/GalconElim\/elim_rankings\/raw\/master\/rank9.png' width=49 height=49 style='margin-top:-100%;margin-bottom:-100%;'\/>", "rating":1246, "alias":"Milky007", "ratingdelta":0, "rank":2, "activity":296, "score":1995}, {"emblem":"<img src='https:\/\/github.com\/GalconElim\/elim_rankings\/raw\/master\/rank9.png' width=49 height=49 style='margin-top:-100%;margin-bottom:-100%;'\/>", "rating":1238, "alias":"Yamamoto79", "ratingdelta":-1, "rank":3, "activity":266, "score":1911}, {"emblem":"<img src='https:\/\/github.com\/GalconElim\/elim_rankings\/raw\/master\/rank9.png' width=49 height=49 style='margin-top:-100%;margin-bottom:-100%;'\/>", "rating":1227, "alias":"GroovyFlame", "ratingdelta":"+3", "rank":4, "activity":217, "score":1792}, {"emblem":"<img src='https:\/\/github.com\/GalconElim\/elim_rankings\/raw\/master\/rank8.png' width=49 height=49 style='margin-top:-100%;margin-bottom:-100%;'\/>", "rating":1209, "alias":"Buz", "ratingdelta":"+2", "rank":5, "activity":446, "score":1612}, {"emblem":"<img src='https:\/\/github.com\/GalconElim\/elim_rankings\/raw\/master\/rank8.png' width=49 height=49 style='margin-top:-100%;margin-bottom:-100%;'\/>", "rating":1195, "alias":"Tiberius88", "ratingdelta":0, "rank":6, "activity":246, "score":1486}, {"emblem":"<img src='https:\/\/github.com\/GalconElim\/elim_rankings\/raw\/master\/rank8.png' width=49 height=49 style='margin-top:-100%;margin-bottom:-100%;'\/>", "rating":1191, "alias":"CloudySheet~353", "ratingdelta":"+3", "rank":7, "activity":368, "score":1456}, {"emblem":"<img src='https:\/\/github.com\/GalconElim\/elim_rankings\/raw\/master\/rank7.png' width=49 height=49 style='margin-top:-100%;margin-bottom:-100%;'\/>", "rating":1184, "alias":"stront01", "ratingdelta":0, "rank":8, "activity":343, "score":1400}, {"emblem":"<img src='https:\/\/github.com\/GalconElim\/elim_rankings\/raw\/master\/rank7.png' width=49 height=49 style='margin-top:-100%;margin-bottom:-100%;'\/>", "rating":1183, "alias":"TangySoda~164", "ratingdelta":-7, "rank":9, "activity":555, "score":1391}, {"emblem":"<img src='https:\/\/github.com\/GalconElim\/elim_rankings\/raw\/master\/rank7.png' width=49 height=49 style='margin-top:-100%;margin-bottom:-100%;'\/>", "rating":1180, "alias":"mintyfresh", "ratingdelta":"+2", "rank":10, "activity":261, "score":1371}, {"emblem":"<img src='https:\/\/github.com\/GalconElim\/elim_rankings\/raw\/master\/rank7.png' width=49 height=49 style='margin-top:-100%;margin-bottom:-100%;'\/>", "rating":1177, "alias":"themadox", "ratingdelta":0, "rank":11, "activity":308, "score":1343}, {"emblem":"<img src='https:\/\/github.com\/GalconElim\/elim_rankings\/raw\/master\/rank7.png' width=49 height=49 style='margin-top:-100%;margin-bottom:-100%;'\/>", "rating":1174, "alias":"Celica", "ratingdelta":0, "rank":12, "activity":311, "score":1324}, {"emblem":"<img src='https:\/\/github.com\/GalconElim\/elim_rankings\/raw\/master\/rank7.png' width=49 height=49 style='margin-top:-100%;margin-bottom:-100%;'\/>", "rating":1172, "alias":"hamidrez", "ratingdelta":0, "rank":13, "activity":165, "score":1305}, {"emblem":"<img src='https:\/\/github.com\/GalconElim\/elim_rankings\/raw\/master\/rank7.png' width=49 height=49 style='margin-top:-100%;margin-bottom:-100%;'\/>", "rating":1171, "alias":"His-Majesty", "ratingdelta":"+1", "rank":14, "activity":476, "score":1301}, {"emblem":"<img src='https:\/\/github.com\/GalconElim\/elim_rankings\/raw\/master\/rank7.png' width=49 height=49 style='margin-top:-100%;margin-bottom:-100%;'\/>", "rating":1165, "alias":"TidyFox-415", "ratingdelta":"+1", "rank":15, "activity":216, "score":1251}, {"emblem":"<img src='https:\/\/github.com\/GalconElim\/elim_rankings\/raw\/master\/rank7.png' width=49 height=49 style='margin-top:-100%;margin-bottom:-100%;'\/>", "rating":1164, "alias":"SwiftFlag~587", "ratingdelta":"+4", "rank":16, "activity":269, "score":1244}, {"emblem":"<img src='https:\/\/github.com\/GalconElim\/elim_rankings\/raw\/master\/rank6.png' width=49 height=49 style='margin-top:-100%;margin-bottom:-100%;'\/>", "rating":1150, "alias":"PR0D1GY", "ratingdelta":"+1", "rank":17, "activity":253, "score":1153}, {"emblem":"<img src='https:\/\/github.com\/GalconElim\/elim_rankings\/raw\/master\/rank6.png' width=49 height=49 style='margin-top:-100%;margin-bottom:-100%;'\/>", "rating":1150, "alias":"BDAT10", "ratingdelta":0, "rank":18, "activity":440, "score":1152}, {"emblem":"<img src='https:\/\/github.com\/GalconElim\/elim_rankings\/raw\/master\/rank6.png' width=49 height=49 style='margin-top:-100%;margin-bottom:-100%;'\/>", "rating":1148, "alias":"jerocco", "ratingdelta":"+1", "rank":19, "activity":612, "score":1135}, {"emblem":"<img src='https:\/\/github.com\/GalconElim\/elim_rankings\/raw\/master\/rank6.png' width=49 height=49 style='margin-top:-100%;margin-bottom:-100%;'\/>", "rating":1146, "alias":"farzip", "ratingdelta":"+2", "rank":20, "activity":186, "score":1125}, {"emblem":"<img src='https:\/\/github.com\/GalconElim\/elim_rankings\/raw\/master\/rank6.png' width=49 height=49 style='margin-top:-100%;margin-bottom:-100%;'\/>", "rating":1138, "alias":"WateryApple~232", "ratingdelta":"+2", "rank":21, "activity":203, "score":1075}, {"emblem":"<img src='https:\/\/github.com\/GalconElim\/elim_rankings\/raw\/master\/rank6.png' width=49 height=49 style='margin-top:-100%;margin-bottom:-100%;'\/>", "rating":1138, "alias":"Kotori", "ratingdelta":"+1", "rank":22, "activity":207, "score":1071}, {"emblem":"<img src='https:\/\/github.com\/GalconElim\/elim_rankings\/raw\/master\/rank6.png' width=49 height=49 style='margin-top:-100%;margin-bottom:-100%;'\/>", "rating":1132, "alias":"worldwarX", "ratingdelta":-5, "rank":23, "activity":470, "score":1039}, {"emblem":"<img src='https:\/\/github.com\/GalconElim\/elim_rankings\/raw\/master\/rank5.png' width=49 height=49 style='margin-top:-100%;margin-bottom:-100%;'\/>", "rating":1113, "alias":"OBTHR33", "ratingdelta":"+2", "rank":24, "activity":429, "score":932}, {"emblem":"<img src='https:\/\/github.com\/GalconElim\/elim_rankings\/raw\/master\/rank5.png' width=49 height=49 style='margin-top:-100%;margin-bottom:-100%;'\/>", "rating":1105, "alias":"lock70", "ratingdelta":0, "rank":25, "activity":124, "score":887}, {"emblem":"<img src='https:\/\/github.com\/GalconElim\/elim_rankings\/raw\/master\/rank5.png' width=49 height=49 style='margin-top:-100%;margin-bottom:-100%;'\/>", "rating":1105, "alias":"Olliec", "ratingdelta":0, "rank":26, "activity":208, "score":887}, {"emblem":"<img src='https:\/\/github.com\/GalconElim\/elim_rankings\/raw\/master\/rank5.png' width=49 height=49 style='margin-top:-100%;margin-bottom:-100%;'\/>", "rating":1105, "alias":"JSU332017", "ratingdelta":-3, "rank":27, "activity":638, "score":886}, {"emblem":"<img src='https:\/\/github.com\/GalconElim\/elim_rankings\/raw\/master\/rank5.png' width=49 height=49 style='margin-top:-100%;margin-bottom:-100%;'\/>", "rating":1098, "alias":"SweetPilot~411", "ratingdelta":"+4", "rank":28, "activity":214, "score":853}, {"emblem":"<img src='https:\/\/github.com\/GalconElim\/elim_rankings\/raw\/master\/rank4.png' width=49 height=49 style='margin-top:-100%;margin-bottom:-100%;'\/>", "rating":1095, "alias":"SaucyFlame~407", "ratingdelta":-3, "rank":29, "activity":300, "score":838}, {"emblem":"<img src='https:\/\/github.com\/GalconElim\/elim_rankings\/raw\/master\/rank4.png' width=49 height=49 style='margin-top:-100%;margin-bottom:-100%;'\/>", "rating":1078, "alias":"QuirkyToad~911", "ratingdelta":"+2", "rank":30, "activity":186, "score":759}, {"emblem":"<img src='https:\/\/github.com\/GalconElim\/elim_rankings\/raw\/master\/rank4.png' width=49 height=49 style='margin-top:-100%;margin-bottom:-100%;'\/>", "rating":1078, "alias":"ZippyComb~184", "ratingdelta":"+1", "rank":31, "activity":248, "score":758}, {"emblem":"<img src='https:\/\/github.com\/GalconElim\/elim_rankings\/raw\/master\/rank4.png' width=49 height=49 style='margin-top:-100%;margin-bottom:-100%;'\/>", "rating":1077, "alias":"dadedread786", "ratingdelta":"+2", "rank":32, "activity":287, "score":754}, {"emblem":"<img src='https:\/\/github.com\/GalconElim\/elim_rankings\/raw\/master\/rank4.png' width=49 height=49 style='margin-top:-100%;margin-bottom:-100%;'\/>", "rating":1073, "alias":"jozin", "ratingdelta":"+5", "rank":33, "activity":321, "score":739}, {"emblem":"<img src='https:\/\/github.com\/GalconElim\/elim_rankings\/raw\/master\/rank4.png' width=49 height=49 style='margin-top:-100%;margin-bottom:-100%;'\/>", "rating":1070, "alias":"buzzderank", "ratingdelta":"+1", "rank":34, "activity":556, "score":726}, {"emblem":"<img src='https:\/\/github.com\/GalconElim\/elim_rankings\/raw\/master\/rank4.png' width=49 height=49 style='margin-top:-100%;margin-bottom:-100%;'\/>", "rating":1069, "alias":"TiMoGeN51", "ratingdelta":0, "rank":35, "activity":225, "score":721}, {"emblem":"<img src='https:\/\/github.com\/GalconElim\/elim_rankings\/raw\/master\/rank4.png' width=49 height=49 style='margin-top:-100%;margin-bottom:-100%;'\/>", "rating":1068, "alias":"DryMango~917", "ratingdelta":0, "rank":36, "activity":212, "score":719}, {"emblem":"<img src='https:\/\/github.com\/GalconElim\/elim_rankings\/raw\/master\/rank3.png' width=49 height=49 style='margin-top:-100%;margin-bottom:-100%;'\/>", "rating":1065, "alias":"Ch1kn", "ratingdelta":"+1", "rank":37, "activity":195, "score":706}, {"emblem":"<img src='https:\/\/github.com\/GalconElim\/elim_rankings\/raw\/master\/rank3.png' width=49 height=49 style='margin-top:-100%;margin-bottom:-100%;'\/>", "rating":1061, "alias":"cohnii", "ratingdelta":"+2", "rank":38, "activity":237, "score":690}, {"emblem":"<img src='https:\/\/github.com\/GalconElim\/elim_rankings\/raw\/master\/rank3.png' width=49 height=49 style='margin-top:-100%;margin-bottom:-100%;'\/>", "rating":1056, "alias":"LuckyPizza", "ratingdelta":"+1", "rank":39, "activity":347, "score":669}, {"emblem":"<img src='https:\/\/github.com\/GalconElim\/elim_rankings\/raw\/master\/rank3.png' width=49 height=49 style='margin-top:-100%;margin-bottom:-100%;'\/>", "rating":1054, "alias":"dfxe", "ratingdelta":"+2", "rank":40, "activity":173, "score":664}, {"emblem":"<img src='https:\/\/github.com\/GalconElim\/elim_rankings\/raw\/master\/rank3.png' width=49 height=49 style='margin-top:-100%;margin-bottom:-100%;'\/>", "rating":1050, "alias":"jib_bles", "ratingdelta":0, "rank":41, "activity":252, "score":648}, {"emblem":"<img src='https:\/\/github.com\/GalconElim\/elim_rankings\/raw\/master\/rank3.png' width=49 height=49 style='margin-top:-100%;margin-bottom:-100%;'\/>", "rating":1050, "alias":"BurlyApple~769", "ratingdelta":0, "rank":42, "activity":271, "score":648}, {"emblem":"<img src='https:\/\/github.com\/GalconElim\/elim_rankings\/raw\/master\/rank3.png' width=49 height=49 style='margin-top:-100%;margin-bottom:-100%;'\/>", "rating":1047, "alias":"Ethanator10", "ratingdelta":0, "rank":43, "activity":197, "score":635}, {"emblem":"<img src='https:\/\/github.com\/GalconElim\/elim_rankings\/raw\/master\/rank3.png' width=49 height=49 style='margin-top:-100%;margin-bottom:-100%;'\/>", "rating":1039, "alias":"Blackdwarf", "ratingdelta":"+1", "rank":44, "activity":153, "score":607}, {"emblem":"<img src='https:\/\/github.com\/GalconElim\/elim_rankings\/raw\/master\/rank2.png' width=49 height=49 style='margin-top:-100%;margin-bottom:-100%;'\/>", "rating":1031, "alias":"RockySpruce~290", "ratingdelta":0, "rank":45, "activity":400, "score":581}, {"emblem":"<img src='https:\/\/github.com\/GalconElim\/elim_rankings\/raw\/master\/rank2.png' width=49 height=49 style='margin-top:-100%;margin-bottom:-100%;'\/>", "rating":1026, "alias":"GrumpyIslan~863", "ratingdelta":0, "rank":46, "activity":214, "score":564}, {"emblem":"<img src='https:\/\/github.com\/GalconElim\/elim_rankings\/raw\/master\/rank2.png' width=49 height=49 style='margin-top:-100%;margin-bottom:-100%;'\/>", "rating":1026, "alias":"SmokyMonkey~899", "ratingdelta":0, "rank":47, "activity":286, "score":562}, {"emblem":"<img src='https:\/\/github.com\/GalconElim\/elim_rankings\/raw\/master\/rank2.png' width=49 height=49 style='margin-top:-100%;margin-bottom:-100%;'\/>", "rating":1013, "alias":"spishnos", "ratingdelta":-2, "rank":48, "activity":236, "score":524}, {"emblem":"<img src='https:\/\/github.com\/GalconElim\/elim_rankings\/raw\/master\/rank2.png' width=49 height=49 style='margin-top:-100%;margin-bottom:-100%;'\/>", "rating":1010, "alias":"LightCrush~620", "ratingdelta":0, "rank":49, "activity":206, "score":513}, {"emblem":"<img src='https:\/\/github.com\/GalconElim\/elim_rankings\/raw\/master\/rank2.png' width=49 height=49 style='margin-top:-100%;margin-bottom:-100%;'\/>", "rating":1009, "alias":"k30", "ratingdelta":-1, "rank":50, "activity":285, "score":510}, {"emblem":"<img src='https:\/\/github.com\/GalconElim\/elim_rankings\/raw\/master\/rank1.png' width=49 height=49 style='margin-top:-100%;margin-bottom:-100%;'\/>", "rating":985, "alias":"FadedAce~233", "ratingdelta":-3, "rank":51, "activity":312, "score":446}, {"emblem":"<img src='https:\/\/github.com\/GalconElim\/elim_rankings\/raw\/master\/rank1.png' width=49 height=49 style='margin-top:-100%;margin-bottom:-100%;'\/>", "rating":974, "alias":"orenong", "ratingdelta":0, "rank":52, "activity":514, "score":418}], "queryRecordCount":52, "totalRecordCount":52}