{"records":[{"emblem":"<img src='https:\/\/github.com\/GalconElim\/elim_rankings\/raw\/master\/rank10.png' width=49 height=49 style='margin-top:-100%;margin-bottom:-100%;'\/>", "rating":1236, "alias":"MusCu", "ratingdelta":0, "rank":1, "activity":196, "score":2959}, {"emblem":"<img src='https:\/\/github.com\/GalconElim\/elim_rankings\/raw\/master\/rank10.png' width=49 height=49 style='margin-top:-100%;margin-bottom:-100%;'\/>", "rating":1196, "alias":"Vadim1707", "ratingdelta":0, "rank":2, "activity":263, "score":2356}, {"emblem":"<img src='https:\/\/github.com\/GalconElim\/elim_rankings\/raw\/master\/rank9.png' width=49 height=49 style='margin-top:-100%;margin-bottom:-100%;'\/>", "rating":1159, "alias":"bejut", "ratingdelta":"+3", "rank":3, "activity":2060, "score":1895}, {"emblem":"<img src='https:\/\/github.com\/GalconElim\/elim_rankings\/raw\/master\/rank8.png' width=49 height=49 style='margin-top:-100%;margin-bottom:-100%;'\/>", "rating":1129, "alias":"Reclamation-", "ratingdelta":0, "rank":4, "activity":438, "score":1597}, {"emblem":"<img src='https:\/\/github.com\/GalconElim\/elim_rankings\/raw\/master\/rank8.png' width=49 height=49 style='margin-top:-100%;margin-bottom:-100%;'\/>", "rating":1119, "alias":"pablo55", "ratingdelta":0, "rank":5, "activity":307, "score":1507}, {"emblem":"<img src='https:\/\/github.com\/GalconElim\/elim_rankings\/raw\/master\/rank8.png' width=49 height=49 style='margin-top:-100%;margin-bottom:-100%;'\/>", "rating":1112, "alias":"vip_genius", "ratingdelta":0, "rank":6, "activity":2966, "score":1446}, {"emblem":"<img src='https:\/\/github.com\/GalconElim\/elim_rankings\/raw\/master\/rank7.png' width=49 height=49 style='margin-top:-100%;margin-bottom:-100%;'\/>", "rating":1105, "alias":"GoOody", "ratingdelta":-3, "rank":7, "activity":1897, "score":1393}, {"emblem":"<img src='https:\/\/github.com\/GalconElim\/elim_rankings\/raw\/master\/rank7.png' width=49 height=49 style='margin-top:-100%;margin-bottom:-100%;'\/>", "rating":1102, "alias":"ss0317", "ratingdelta":-1, "rank":8, "activity":2570, "score":1366}, {"emblem":"<img src='https:\/\/github.com\/GalconElim\/elim_rankings\/raw\/master\/rank7.png' width=49 height=49 style='margin-top:-100%;margin-bottom:-100%;'\/>", "rating":1090, "alias":"waffle3z", "ratingdelta":0, "rank":9, "activity":162, "score":1276}, {"emblem":"<img src='https:\/\/github.com\/GalconElim\/elim_rankings\/raw\/master\/rank7.png' width=49 height=49 style='margin-top:-100%;margin-bottom:-100%;'\/>", "rating":1086, "alias":"mafl", "ratingdelta":0, "rank":10, "activity":236, "score":1245}, {"emblem":"<img src='https:\/\/github.com\/GalconElim\/elim_rankings\/raw\/master\/rank7.png' width=49 height=49 style='margin-top:-100%;margin-bottom:-100%;'\/>", "rating":1083, "alias":"JDHA218", "ratingdelta":0, "rank":11, "activity":555, "score":1229}, {"emblem":"<img src='https:\/\/github.com\/GalconElim\/elim_rankings\/raw\/master\/rank7.png' width=49 height=49 style='margin-top:-100%;margin-bottom:-100%;'\/>", "rating":1083, "alias":"SyMSyMmY", "ratingdelta":0, "rank":12, "activity":316, "score":1227}, {"emblem":"<img src='https:\/\/github.com\/GalconElim\/elim_rankings\/raw\/master\/rank6.png' width=49 height=49 style='margin-top:-100%;margin-bottom:-100%;'\/>", "rating":1070, "alias":"katudondayo", "ratingdelta":0, "rank":13, "activity":354, "score":1138}, {"emblem":"<img src='https:\/\/github.com\/GalconElim\/elim_rankings\/raw\/master\/rank6.png' width=49 height=49 style='margin-top:-100%;margin-bottom:-100%;'\/>", "rating":1062, "alias":"Eudaemonia", "ratingdelta":0, "rank":14, "activity":116, "score":1089}, {"emblem":"<img src='https:\/\/github.com\/GalconElim\/elim_rankings\/raw\/master\/rank6.png' width=49 height=49 style='margin-top:-100%;margin-bottom:-100%;'\/>", "rating":1059, "alias":"Parko", "ratingdelta":0, "rank":15, "activity":125, "score":1071}, {"emblem":"<img src='https:\/\/github.com\/GalconElim\/elim_rankings\/raw\/master\/rank6.png' width=49 height=49 style='margin-top:-100%;margin-bottom:-100%;'\/>", "rating":1058, "alias":"EternalFlame", "ratingdelta":"+1", "rank":16, "activity":1382, "score":1062}, {"emblem":"<img src='https:\/\/github.com\/GalconElim\/elim_rankings\/raw\/master\/rank5.png' width=49 height=49 style='margin-top:-100%;margin-bottom:-100%;'\/>", "rating":1046, "alias":"SadGalaxy360", "ratingdelta":0, "rank":17, "activity":1048, "score":993}, {"emblem":"<img src='https:\/\/github.com\/GalconElim\/elim_rankings\/raw\/master\/rank5.png' width=49 height=49 style='margin-top:-100%;margin-bottom:-100%;'\/>", "rating":1044, "alias":"like.a.ninja", "ratingdelta":0, "rank":18, "activity":358, "score":978}, {"emblem":"<img src='https:\/\/github.com\/GalconElim\/elim_rankings\/raw\/master\/rank5.png' width=49 height=49 style='margin-top:-100%;margin-bottom:-100%;'\/>", "rating":1042, "alias":"oculterito", "ratingdelta":0, "rank":19, "activity":380, "score":968}, {"emblem":"<img src='https:\/\/github.com\/GalconElim\/elim_rankings\/raw\/master\/rank5.png' width=49 height=49 style='margin-top:-100%;margin-bottom:-100%;'\/>", "rating":1041, "alias":"zeropoint", "ratingdelta":0, "rank":20, "activity":144, "score":963}, {"emblem":"<img src='https:\/\/github.com\/GalconElim\/elim_rankings\/raw\/master\/rank5.png' width=49 height=49 style='margin-top:-100%;margin-bottom:-100%;'\/>", "rating":1040, "alias":"gmoe", "ratingdelta":0, "rank":21, "activity":156, "score":959}, {"emblem":"<img src='https:\/\/github.com\/GalconElim\/elim_rankings\/raw\/master\/rank5.png' width=49 height=49 style='margin-top:-100%;margin-bottom:-100%;'\/>", "rating":1037, "alias":"Yellow_Flash", "ratingdelta":0, "rank":22, "activity":228, "score":941}, {"emblem":"<img src='https:\/\/github.com\/GalconElim\/elim_rankings\/raw\/master\/rank5.png' width=49 height=49 style='margin-top:-100%;margin-bottom:-100%;'\/>", "rating":1035, "alias":"sadpanda", "ratingdelta":0, "rank":23, "activity":146, "score":932}, {"emblem":"<img src='https:\/\/github.com\/GalconElim\/elim_rankings\/raw\/master\/rank5.png' width=49 height=49 style='margin-top:-100%;margin-bottom:-100%;'\/>", "rating":1035, "alias":"mills14", "ratingdelta":0, "rank":24, "activity":213, "score":928}, {"emblem":"<img src='https:\/\/github.com\/GalconElim\/elim_rankings\/raw\/master\/rank5.png' width=49 height=49 style='margin-top:-100%;margin-bottom:-100%;'\/>", "rating":1034, "alias":"Captain-Levi", "ratingdelta":0, "rank":25, "activity":154, "score":926}, {"emblem":"<img src='https:\/\/github.com\/GalconElim\/elim_rankings\/raw\/master\/rank5.png' width=49 height=49 style='margin-top:-100%;margin-bottom:-100%;'\/>", "rating":1027, "alias":"NosyToast~892", "ratingdelta":0, "rank":26, "activity":257, "score":890}, {"emblem":"<img src='https:\/\/github.com\/GalconElim\/elim_rankings\/raw\/master\/rank4.png' width=49 height=49 style='margin-top:-100%;margin-bottom:-100%;'\/>", "rating":1016, "alias":"proxywar", "ratingdelta":0, "rank":27, "activity":147, "score":836}, {"emblem":"<img src='https:\/\/github.com\/GalconElim\/elim_rankings\/raw\/master\/rank4.png' width=49 height=49 style='margin-top:-100%;margin-bottom:-100%;'\/>", "rating":1008, "alias":"thehurricane", "ratingdelta":0, "rank":28, "activity":154, "score":797}, {"emblem":"<img src='https:\/\/github.com\/GalconElim\/elim_rankings\/raw\/master\/rank4.png' width=49 height=49 style='margin-top:-100%;margin-bottom:-100%;'\/>", "rating":1005, "alias":"Ardi09.", "ratingdelta":0, "rank":29, "activity":714, "score":782}, {"emblem":"<img src='https:\/\/github.com\/GalconElim\/elim_rankings\/raw\/master\/rank4.png' width=49 height=49 style='margin-top:-100%;margin-bottom:-100%;'\/>", "rating":998, "alias":"ciubaka", "ratingdelta":-5, "rank":30, "activity":1140, "score":754}, {"emblem":"<img src='https:\/\/github.com\/GalconElim\/elim_rankings\/raw\/master\/rank4.png' width=49 height=49 style='margin-top:-100%;margin-bottom:-100%;'\/>", "rating":997, "alias":"milkyway", "ratingdelta":0, "rank":31, "activity":2575, "score":748}, {"emblem":"<img src='https:\/\/github.com\/GalconElim\/elim_rankings\/raw\/master\/rank4.png' width=49 height=49 style='margin-top:-100%;margin-bottom:-100%;'\/>", "rating":995, "alias":"Uranus-98", "ratingdelta":"+1", "rank":32, "activity":1078, "score":738}, {"emblem":"<img src='https:\/\/github.com\/GalconElim\/elim_rankings\/raw\/master\/rank4.png' width=49 height=49 style='margin-top:-100%;margin-bottom:-100%;'\/>", "rating":990, "alias":"icomeinpeece", "ratingdelta":0, "rank":33, "activity":2747, "score":717}, {"emblem":"<img src='https:\/\/github.com\/GalconElim\/elim_rankings\/raw\/master\/rank3.png' width=49 height=49 style='margin-top:-100%;margin-bottom:-100%;'\/>", "rating":977, "alias":"Sondair", "ratingdelta":-2, "rank":34, "activity":2508, "score":664}, {"emblem":"<img src='https:\/\/github.com\/GalconElim\/elim_rankings\/raw\/master\/rank3.png' width=49 height=49 style='margin-top:-100%;margin-bottom:-100%;'\/>", "rating":975, "alias":"GenghisCon", "ratingdelta":0, "rank":35, "activity":222, "score":660}, {"emblem":"<img src='https:\/\/github.com\/GalconElim\/elim_rankings\/raw\/master\/rank2.png' width=49 height=49 style='margin-top:-100%;margin-bottom:-100%;'\/>", "rating":955, "alias":"Chris280tian", "ratingdelta":0, "rank":36, "activity":385, "score":588}, {"emblem":"<img src='https:\/\/github.com\/GalconElim\/elim_rankings\/raw\/master\/rank2.png' width=49 height=49 style='margin-top:-100%;margin-bottom:-100%;'\/>", "rating":952, "alias":"rickss", "ratingdelta":0, "rank":37, "activity":253, "score":578}, {"emblem":"<img src='https:\/\/github.com\/GalconElim\/elim_rankings\/raw\/master\/rank2.png' width=49 height=49 style='margin-top:-100%;margin-bottom:-100%;'\/>", "rating":947, "alias":"CoolFaucet~518", "ratingdelta":-6, "rank":38, "activity":1836, "score":560}, {"emblem":"<img src='https:\/\/github.com\/GalconElim\/elim_rankings\/raw\/master\/rank1.png' width=49 height=49 style='margin-top:-100%;margin-bottom:-100%;'\/>", "rating":905, "alias":"x-Carbon-x", "ratingdelta":0, "rank":39, "activity":414, "score":440}, {"emblem":"<img src='https:\/\/github.com\/GalconElim\/elim_rankings\/raw\/master\/rank1.png' width=49 height=49 style='margin-top:-100%;margin-bottom:-100%;'\/>", "rating":904, "alias":"duruti", "ratingdelta":0, "rank":40, "activity":668, "score":438}, {"emblem":"<img src='https:\/\/github.com\/GalconElim\/elim_rankings\/raw\/master\/rank1.png' width=49 height=49 style='margin-top:-100%;margin-bottom:-100%;'\/>", "rating":889, "alias":"monguesto", "ratingdelta":-2, "rank":41, "activity":1100, "score":402}, {"emblem":"<img src='https:\/\/github.com\/GalconElim\/elim_rankings\/raw\/master\/rank1.png' width=49 height=49 style='margin-top:-100%;margin-bottom:-100%;'\/>", "rating":883, "alias":"quickmill", "ratingdelta":0, "rank":42, "activity":468, "score":388}, {"emblem":"<img src='https:\/\/github.com\/GalconElim\/elim_rankings\/raw\/master\/rank1.png' width=49 height=49 style='margin-top:-100%;margin-bottom:-100%;'\/>", "rating":832, "alias":"Ares8", "ratingdelta":0, "rank":43, "activity":678, "score":289}, {"emblem":"<img src='https:\/\/github.com\/GalconElim\/elim_rankings\/raw\/master\/rank1.png' width=49 height=49 style='margin-top:-100%;margin-bottom:-100%;'\/>", "rating":832, "alias":"AlGalcone", "ratingdelta":"+1", "rank":44, "activity":638, "score":289}], "queryRecordCount":44, "totalRecordCount":44}