{"records":[{"emblem":"<img src='https:\/\/github.com\/GalconElim\/elim_rankings\/raw\/master\/rank10.png' width=49 height=49 style='margin-top:-100%;margin-bottom:-100%;'\/>", "rating":1274, "alias":"Artimal_PL", "ratingdelta":0, "rank":1, "activity":341, "score":3812}, {"emblem":"<img src='https:\/\/github.com\/GalconElim\/elim_rankings\/raw\/master\/rank10.png' width=49 height=49 style='margin-top:-100%;margin-bottom:-100%;'\/>", "rating":1266, "alias":"shunrai", "ratingdelta":-2, "rank":2, "activity":291, "score":3638}, {"emblem":"<img src='https:\/\/github.com\/GalconElim\/elim_rankings\/raw\/master\/rank10.png' width=49 height=49 style='margin-top:-100%;margin-bottom:-100%;'\/>", "rating":1231, "alias":"Disciplina", "ratingdelta":-1, "rank":3, "activity":342, "score":2979}, {"emblem":"<img src='https:\/\/github.com\/GalconElim\/elim_rankings\/raw\/master\/rank10.png' width=49 height=49 style='margin-top:-100%;margin-bottom:-100%;'\/>", "rating":1230, "alias":"Xoi", "ratingdelta":0, "rank":4, "activity":206, "score":2957}, {"emblem":"<img src='https:\/\/github.com\/GalconElim\/elim_rankings\/raw\/master\/rank10.png' width=49 height=49 style='margin-top:-100%;margin-bottom:-100%;'\/>", "rating":1215, "alias":"croissant", "ratingdelta":-2, "rank":5, "activity":590, "score":2711}, {"emblem":"<img src='https:\/\/github.com\/GalconElim\/elim_rankings\/raw\/master\/rank10.png' width=49 height=49 style='margin-top:-100%;margin-bottom:-100%;'\/>", "rating":1213, "alias":"WickedPizza~656", "ratingdelta":"+1", "rank":6, "activity":248, "score":2687}, {"emblem":"<img src='https:\/\/github.com\/GalconElim\/elim_rankings\/raw\/master\/rank10.png' width=49 height=49 style='margin-top:-100%;margin-bottom:-100%;'\/>", "rating":1195, "alias":"Parko", "ratingdelta":0, "rank":7, "activity":124, "score":2421}, {"emblem":"<img src='https:\/\/github.com\/GalconElim\/elim_rankings\/raw\/master\/rank10.png' width=49 height=49 style='margin-top:-100%;margin-bottom:-100%;'\/>", "rating":1192, "alias":"JazzyDeer", "ratingdelta":0, "rank":8, "activity":334, "score":2384}, {"emblem":"<img src='https:\/\/github.com\/GalconElim\/elim_rankings\/raw\/master\/rank10.png' width=49 height=49 style='margin-top:-100%;margin-bottom:-100%;'\/>", "rating":1184, "alias":"someOnh", "ratingdelta":-2, "rank":9, "activity":439, "score":2270}, {"emblem":"<img src='https:\/\/github.com\/GalconElim\/elim_rankings\/raw\/master\/rank10.png' width=49 height=49 style='margin-top:-100%;margin-bottom:-100%;'\/>", "rating":1165, "alias":"JCC", "ratingdelta":0, "rank":10, "activity":44, "score":2036}, {"emblem":"<img src='https:\/\/github.com\/GalconElim\/elim_rankings\/raw\/master\/rank10.png' width=49 height=49 style='margin-top:-100%;margin-bottom:-100%;'\/>", "rating":1164, "alias":"Kraken809", "ratingdelta":0, "rank":11, "activity":71, "score":2026}, {"emblem":"<img src='https:\/\/github.com\/GalconElim\/elim_rankings\/raw\/master\/rank10.png' width=49 height=49 style='margin-top:-100%;margin-bottom:-100%;'\/>", "rating":1162, "alias":"pure1", "ratingdelta":0, "rank":12, "activity":364, "score":2003}, {"emblem":"<img src='https:\/\/github.com\/GalconElim\/elim_rankings\/raw\/master\/rank10.png' width=49 height=49 style='margin-top:-100%;margin-bottom:-100%;'\/>", "rating":1162, "alias":"no.yes", "ratingdelta":0, "rank":13, "activity":789, "score":2001}, {"emblem":"<img src='https:\/\/github.com\/GalconElim\/elim_rankings\/raw\/master\/rank9.png' width=49 height=49 style='margin-top:-100%;margin-bottom:-100%;'\/>", "rating":1157, "alias":"TimeBreaker", "ratingdelta":0, "rank":14, "activity":153, "score":1949}, {"emblem":"<img src='https:\/\/github.com\/GalconElim\/elim_rankings\/raw\/master\/rank9.png' width=49 height=49 style='margin-top:-100%;margin-bottom:-100%;'\/>", "rating":1155, "alias":"mr.oujia", "ratingdelta":"+6", "rank":15, "activity":1062, "score":1929}, {"emblem":"<img src='https:\/\/github.com\/GalconElim\/elim_rankings\/raw\/master\/rank9.png' width=49 height=49 style='margin-top:-100%;margin-bottom:-100%;'\/>", "rating":1155, "alias":"CsAsTra", "ratingdelta":-4, "rank":16, "activity":471, "score":1925}, {"emblem":"<img src='https:\/\/github.com\/GalconElim\/elim_rankings\/raw\/master\/rank9.png' width=49 height=49 style='margin-top:-100%;margin-bottom:-100%;'\/>", "rating":1148, "alias":"sirgrapeLot", "ratingdelta":0, "rank":17, "activity":49, "score":1852}, {"emblem":"<img src='https:\/\/github.com\/GalconElim\/elim_rankings\/raw\/master\/rank9.png' width=49 height=49 style='margin-top:-100%;margin-bottom:-100%;'\/>", "rating":1142, "alias":"JMan8080", "ratingdelta":"+1", "rank":18, "activity":139, "score":1788}, {"emblem":"<img src='https:\/\/github.com\/GalconElim\/elim_rankings\/raw\/master\/rank8.png' width=49 height=49 style='margin-top:-100%;margin-bottom:-100%;'\/>", "rating":1129, "alias":"milkyway", "ratingdelta":"+7", "rank":19, "activity":2195, "score":1657}, {"emblem":"<img src='https:\/\/github.com\/GalconElim\/elim_rankings\/raw\/master\/rank8.png' width=49 height=49 style='margin-top:-100%;margin-bottom:-100%;'\/>", "rating":1128, "alias":"SupiorLemon", "ratingdelta":0, "rank":20, "activity":265, "score":1648}, {"emblem":"<img src='https:\/\/github.com\/GalconElim\/elim_rankings\/raw\/master\/rank8.png' width=49 height=49 style='margin-top:-100%;margin-bottom:-100%;'\/>", "rating":1123, "alias":"bmvj", "ratingdelta":0, "rank":21, "activity":102, "score":1602}, {"emblem":"<img src='https:\/\/github.com\/GalconElim\/elim_rankings\/raw\/master\/rank8.png' width=49 height=49 style='margin-top:-100%;margin-bottom:-100%;'\/>", "rating":1122, "alias":"JeffDoughnut", "ratingdelta":0, "rank":22, "activity":43, "score":1588}, {"emblem":"<img src='https:\/\/github.com\/GalconElim\/elim_rankings\/raw\/master\/rank8.png' width=49 height=49 style='margin-top:-100%;margin-bottom:-100%;'\/>", "rating":1121, "alias":"JDHA218", "ratingdelta":0, "rank":23, "activity":100, "score":1579}, {"emblem":"<img src='https:\/\/github.com\/GalconElim\/elim_rankings\/raw\/master\/rank8.png' width=49 height=49 style='margin-top:-100%;margin-bottom:-100%;'\/>", "rating":1121, "alias":"gmoe", "ratingdelta":0, "rank":24, "activity":89, "score":1577}, {"emblem":"<img src='https:\/\/github.com\/GalconElim\/elim_rankings\/raw\/master\/rank8.png' width=49 height=49 style='margin-top:-100%;margin-bottom:-100%;'\/>", "rating":1118, "alias":"GaudyWeasel", "ratingdelta":0, "rank":25, "activity":209, "score":1558}, {"emblem":"<img src='https:\/\/github.com\/GalconElim\/elim_rankings\/raw\/master\/rank8.png' width=49 height=49 style='margin-top:-100%;margin-bottom:-100%;'\/>", "rating":1116, "alias":"metbo", "ratingdelta":-2, "rank":26, "activity":144, "score":1539}, {"emblem":"<img src='https:\/\/github.com\/GalconElim\/elim_rankings\/raw\/master\/rank8.png' width=49 height=49 style='margin-top:-100%;margin-bottom:-100%;'\/>", "rating":1116, "alias":"hobbes313", "ratingdelta":0, "rank":27, "activity":291, "score":1536}, {"emblem":"<img src='https:\/\/github.com\/GalconElim\/elim_rankings\/raw\/master\/rank8.png' width=49 height=49 style='margin-top:-100%;margin-bottom:-100%;'\/>", "rating":1113, "alias":"DaCAP", "ratingdelta":0, "rank":28, "activity":245, "score":1513}, {"emblem":"<img src='https:\/\/github.com\/GalconElim\/elim_rankings\/raw\/master\/rank8.png' width=49 height=49 style='margin-top:-100%;margin-bottom:-100%;'\/>", "rating":1112, "alias":"mafl", "ratingdelta":0, "rank":29, "activity":587, "score":1503}, {"emblem":"<img src='https:\/\/github.com\/GalconElim\/elim_rankings\/raw\/master\/rank8.png' width=49 height=49 style='margin-top:-100%;margin-bottom:-100%;'\/>", "rating":1110, "alias":"FaZzY", "ratingdelta":0, "rank":30, "activity":212, "score":1483}, {"emblem":"<img src='https:\/\/github.com\/GalconElim\/elim_rankings\/raw\/master\/rank8.png' width=49 height=49 style='margin-top:-100%;margin-bottom:-100%;'\/>", "rating":1107, "alias":"doeish", "ratingdelta":0, "rank":31, "activity":35, "score":1457}, {"emblem":"<img src='https:\/\/github.com\/GalconElim\/elim_rankings\/raw\/master\/rank8.png' width=49 height=49 style='margin-top:-100%;margin-bottom:-100%;'\/>", "rating":1104, "alias":"GO4chips", "ratingdelta":"+1", "rank":32, "activity":725, "score":1438}, {"emblem":"<img src='https:\/\/github.com\/GalconElim\/elim_rankings\/raw\/master\/rank7.png' width=49 height=49 style='margin-top:-100%;margin-bottom:-100%;'\/>", "rating":1100, "alias":"vip_genius", "ratingdelta":-4, "rank":33, "activity":941, "score":1405}, {"emblem":"<img src='https:\/\/github.com\/GalconElim\/elim_rankings\/raw\/master\/rank7.png' width=49 height=49 style='margin-top:-100%;margin-bottom:-100%;'\/>", "rating":1095, "alias":"MadDookie", "ratingdelta":"+2", "rank":34, "activity":3514, "score":1363}, {"emblem":"<img src='https:\/\/github.com\/GalconElim\/elim_rankings\/raw\/master\/rank7.png' width=49 height=49 style='margin-top:-100%;margin-bottom:-100%;'\/>", "rating":1095, "alias":"Fluffywolf", "ratingdelta":0, "rank":35, "activity":94, "score":1361}, {"emblem":"<img src='https:\/\/github.com\/GalconElim\/elim_rankings\/raw\/master\/rank7.png' width=49 height=49 style='margin-top:-100%;margin-bottom:-100%;'\/>", "rating":1093, "alias":"ghost_face", "ratingdelta":0, "rank":36, "activity":168, "score":1343}, {"emblem":"<img src='https:\/\/github.com\/GalconElim\/elim_rankings\/raw\/master\/rank7.png' width=49 height=49 style='margin-top:-100%;margin-bottom:-100%;'\/>", "rating":1091, "alias":"eLemeNt.", "ratingdelta":-2, "rank":37, "activity":601, "score":1330}, {"emblem":"<img src='https:\/\/github.com\/GalconElim\/elim_rankings\/raw\/master\/rank7.png' width=49 height=49 style='margin-top:-100%;margin-bottom:-100%;'\/>", "rating":1091, "alias":"TyCho2", "ratingdelta":0, "rank":38, "activity":37, "score":1330}, {"emblem":"<img src='https:\/\/github.com\/GalconElim\/elim_rankings\/raw\/master\/rank7.png' width=49 height=49 style='margin-top:-100%;margin-bottom:-100%;'\/>", "rating":1090, "alias":"NiftyBread~997", "ratingdelta":0, "rank":39, "activity":122, "score":1320}, {"emblem":"<img src='https:\/\/github.com\/GalconElim\/elim_rankings\/raw\/master\/rank7.png' width=49 height=49 style='margin-top:-100%;margin-bottom:-100%;'\/>", "rating":1089, "alias":"Ovalrebel", "ratingdelta":"+3", "rank":40, "activity":333, "score":1315}, {"emblem":"<img src='https:\/\/github.com\/GalconElim\/elim_rankings\/raw\/master\/rank7.png' width=49 height=49 style='margin-top:-100%;margin-bottom:-100%;'\/>", "rating":1087, "alias":"sugarwalls", "ratingdelta":-1, "rank":41, "activity":433, "score":1299}, {"emblem":"<img src='https:\/\/github.com\/GalconElim\/elim_rankings\/raw\/master\/rank7.png' width=49 height=49 style='margin-top:-100%;margin-bottom:-100%;'\/>", "rating":1086, "alias":"GooZok", "ratingdelta":0, "rank":42, "activity":54, "score":1294}, {"emblem":"<img src='https:\/\/github.com\/GalconElim\/elim_rankings\/raw\/master\/rank7.png' width=49 height=49 style='margin-top:-100%;margin-bottom:-100%;'\/>", "rating":1086, "alias":"Yogensha-", "ratingdelta":0, "rank":43, "activity":76, "score":1291}, {"emblem":"<img src='https:\/\/github.com\/GalconElim\/elim_rankings\/raw\/master\/rank7.png' width=49 height=49 style='margin-top:-100%;margin-bottom:-100%;'\/>", "rating":1085, "alias":"GoOody", "ratingdelta":0, "rank":44, "activity":45, "score":1282}, {"emblem":"<img src='https:\/\/github.com\/GalconElim\/elim_rankings\/raw\/master\/rank7.png' width=49 height=49 style='margin-top:-100%;margin-bottom:-100%;'\/>", "rating":1084, "alias":"Silver-", "ratingdelta":0, "rank":45, "activity":533, "score":1281}, {"emblem":"<img src='https:\/\/github.com\/GalconElim\/elim_rankings\/raw\/master\/rank7.png' width=49 height=49 style='margin-top:-100%;margin-bottom:-100%;'\/>", "rating":1083, "alias":"syrius", "ratingdelta":0, "rank":46, "activity":92, "score":1271}, {"emblem":"<img src='https:\/\/github.com\/GalconElim\/elim_rankings\/raw\/master\/rank7.png' width=49 height=49 style='margin-top:-100%;margin-bottom:-100%;'\/>", "rating":1080, "alias":"Ardi09.", "ratingdelta":-2, "rank":47, "activity":517, "score":1249}, {"emblem":"<img src='https:\/\/github.com\/GalconElim\/elim_rankings\/raw\/master\/rank7.png' width=49 height=49 style='margin-top:-100%;margin-bottom:-100%;'\/>", "rating":1080, "alias":"cricric", "ratingdelta":0, "rank":48, "activity":423, "score":1249}, {"emblem":"<img src='https:\/\/github.com\/GalconElim\/elim_rankings\/raw\/master\/rank7.png' width=49 height=49 style='margin-top:-100%;margin-bottom:-100%;'\/>", "rating":1073, "alias":"Enlights", "ratingdelta":0, "rank":49, "activity":118, "score":1199}, {"emblem":"<img src='https:\/\/github.com\/GalconElim\/elim_rankings\/raw\/master\/rank6.png' width=49 height=49 style='margin-top:-100%;margin-bottom:-100%;'\/>", "rating":1070, "alias":"quickmill", "ratingdelta":"+4", "rank":50, "activity":776, "score":1179}, {"emblem":"<img src='https:\/\/github.com\/GalconElim\/elim_rankings\/raw\/master\/rank6.png' width=49 height=49 style='margin-top:-100%;margin-bottom:-100%;'\/>", "rating":1070, "alias":"ruBEARRx", "ratingdelta":0, "rank":51, "activity":686, "score":1178}, {"emblem":"<img src='https:\/\/github.com\/GalconElim\/elim_rankings\/raw\/master\/rank6.png' width=49 height=49 style='margin-top:-100%;margin-bottom:-100%;'\/>", "rating":1070, "alias":"FancyCar~225", "ratingdelta":"+9", "rank":52, "activity":356, "score":1178}, {"emblem":"<img src='https:\/\/github.com\/GalconElim\/elim_rankings\/raw\/master\/rank6.png' width=49 height=49 style='margin-top:-100%;margin-bottom:-100%;'\/>", "rating":1070, "alias":"ccgn", "ratingdelta":-2, "rank":53, "activity":263, "score":1176}, {"emblem":"<img src='https:\/\/github.com\/GalconElim\/elim_rankings\/raw\/master\/rank6.png' width=49 height=49 style='margin-top:-100%;margin-bottom:-100%;'\/>", "rating":1069, "alias":"zeropoint", "ratingdelta":0, "rank":54, "activity":932, "score":1174}, {"emblem":"<img src='https:\/\/github.com\/GalconElim\/elim_rankings\/raw\/master\/rank6.png' width=49 height=49 style='margin-top:-100%;margin-bottom:-100%;'\/>", "rating":1069, "alias":"SlickRick61", "ratingdelta":"+3", "rank":55, "activity":454, "score":1170}, {"emblem":"<img src='https:\/\/github.com\/GalconElim\/elim_rankings\/raw\/master\/rank6.png' width=49 height=49 style='margin-top:-100%;margin-bottom:-100%;'\/>", "rating":1068, "alias":"Tylermbcs16", "ratingdelta":0, "rank":56, "activity":106, "score":1167}, {"emblem":"<img src='https:\/\/github.com\/GalconElim\/elim_rankings\/raw\/master\/rank6.png' width=49 height=49 style='margin-top:-100%;margin-bottom:-100%;'\/>", "rating":1066, "alias":"TimDebJon", "ratingdelta":0, "rank":57, "activity":221, "score":1153}, {"emblem":"<img src='https:\/\/github.com\/GalconElim\/elim_rankings\/raw\/master\/rank6.png' width=49 height=49 style='margin-top:-100%;margin-bottom:-100%;'\/>", "rating":1066, "alias":"uranus-98", "ratingdelta":"+3", "rank":58, "activity":324, "score":1152}, {"emblem":"<img src='https:\/\/github.com\/GalconElim\/elim_rankings\/raw\/master\/rank6.png' width=49 height=49 style='margin-top:-100%;margin-bottom:-100%;'\/>", "rating":1065, "alias":"CoolFaucet~518", "ratingdelta":0, "rank":59, "activity":580, "score":1145}, {"emblem":"<img src='https:\/\/github.com\/GalconElim\/elim_rankings\/raw\/master\/rank6.png' width=49 height=49 style='margin-top:-100%;margin-bottom:-100%;'\/>", "rating":1064, "alias":"likeag66", "ratingdelta":"+1", "rank":60, "activity":356, "score":1141}, {"emblem":"<img src='https:\/\/github.com\/GalconElim\/elim_rankings\/raw\/master\/rank6.png' width=49 height=49 style='margin-top:-100%;margin-bottom:-100%;'\/>", "rating":1063, "alias":"osnoz", "ratingdelta":0, "rank":61, "activity":60, "score":1134}, {"emblem":"<img src='https:\/\/github.com\/GalconElim\/elim_rankings\/raw\/master\/rank6.png' width=49 height=49 style='margin-top:-100%;margin-bottom:-100%;'\/>", "rating":1063, "alias":"jbperez808", "ratingdelta":0, "rank":62, "activity":301, "score":1130}, {"emblem":"<img src='https:\/\/github.com\/GalconElim\/elim_rankings\/raw\/master\/rank6.png' width=49 height=49 style='margin-top:-100%;margin-bottom:-100%;'\/>", "rating":1062, "alias":"Reclamation-", "ratingdelta":0, "rank":63, "activity":117, "score":1128}, {"emblem":"<img src='https:\/\/github.com\/GalconElim\/elim_rankings\/raw\/master\/rank6.png' width=49 height=49 style='margin-top:-100%;margin-bottom:-100%;'\/>", "rating":1059, "alias":"noa-B", "ratingdelta":"+1", "rank":64, "activity":206, "score":1109}, {"emblem":"<img src='https:\/\/github.com\/GalconElim\/elim_rankings\/raw\/master\/rank6.png' width=49 height=49 style='margin-top:-100%;margin-bottom:-100%;'\/>", "rating":1059, "alias":"creaky2", "ratingdelta":"+11", "rank":65, "activity":226, "score":1108}, {"emblem":"<img src='https:\/\/github.com\/GalconElim\/elim_rankings\/raw\/master\/rank6.png' width=49 height=49 style='margin-top:-100%;margin-bottom:-100%;'\/>", "rating":1058, "alias":"yeasonn", "ratingdelta":0, "rank":66, "activity":445, "score":1101}, {"emblem":"<img src='https:\/\/github.com\/GalconElim\/elim_rankings\/raw\/master\/rank6.png' width=49 height=49 style='margin-top:-100%;margin-bottom:-100%;'\/>", "rating":1058, "alias":"Buz", "ratingdelta":"+5", "rank":67, "activity":140, "score":1099}, {"emblem":"<img src='https:\/\/github.com\/GalconElim\/elim_rankings\/raw\/master\/rank6.png' width=49 height=49 style='margin-top:-100%;margin-bottom:-100%;'\/>", "rating":1057, "alias":"jennygirl", "ratingdelta":"+10", "rank":68, "activity":2267, "score":1096}, {"emblem":"<img src='https:\/\/github.com\/GalconElim\/elim_rankings\/raw\/master\/rank6.png' width=49 height=49 style='margin-top:-100%;margin-bottom:-100%;'\/>", "rating":1056, "alias":"Faye-", "ratingdelta":0, "rank":69, "activity":279, "score":1090}, {"emblem":"<img src='https:\/\/github.com\/GalconElim\/elim_rankings\/raw\/master\/rank6.png' width=49 height=49 style='margin-top:-100%;margin-bottom:-100%;'\/>", "rating":1053, "alias":"MAKki", "ratingdelta":-4, "rank":70, "activity":787, "score":1068}, {"emblem":"<img src='https:\/\/github.com\/GalconElim\/elim_rankings\/raw\/master\/rank6.png' width=49 height=49 style='margin-top:-100%;margin-bottom:-100%;'\/>", "rating":1053, "alias":"goner", "ratingdelta":0, "rank":71, "activity":65, "score":1067}, {"emblem":"<img src='https:\/\/github.com\/GalconElim\/elim_rankings\/raw\/master\/rank6.png' width=49 height=49 style='margin-top:-100%;margin-bottom:-100%;'\/>", "rating":1052, "alias":"qUidNovI", "ratingdelta":"+1", "rank":72, "activity":1106, "score":1064}, {"emblem":"<img src='https:\/\/github.com\/GalconElim\/elim_rankings\/raw\/master\/rank6.png' width=49 height=49 style='margin-top:-100%;margin-bottom:-100%;'\/>", "rating":1051, "alias":"K1LL3rW33D", "ratingdelta":-11, "rank":73, "activity":681, "score":1060}, {"emblem":"<img src='https:\/\/github.com\/GalconElim\/elim_rankings\/raw\/master\/rank6.png' width=49 height=49 style='margin-top:-100%;margin-bottom:-100%;'\/>", "rating":1051, "alias":"drhillikilil", "ratingdelta":"+4", "rank":74, "activity":898, "score":1059}, {"emblem":"<img src='https:\/\/github.com\/GalconElim\/elim_rankings\/raw\/master\/rank6.png' width=49 height=49 style='margin-top:-100%;margin-bottom:-100%;'\/>", "rating":1051, "alias":"CurlyPeach~218", "ratingdelta":0, "rank":75, "activity":532, "score":1057}, {"emblem":"<img src='https:\/\/github.com\/GalconElim\/elim_rankings\/raw\/master\/rank6.png' width=49 height=49 style='margin-top:-100%;margin-bottom:-100%;'\/>", "rating":1051, "alias":"SweetOgre~435", "ratingdelta":0, "rank":76, "activity":59, "score":1057}, {"emblem":"<img src='https:\/\/github.com\/GalconElim\/elim_rankings\/raw\/master\/rank6.png' width=49 height=49 style='margin-top:-100%;margin-bottom:-100%;'\/>", "rating":1050, "alias":"fullofspite", "ratingdelta":-1, "rank":77, "activity":210, "score":1050}, {"emblem":"<img src='https:\/\/github.com\/GalconElim\/elim_rankings\/raw\/master\/rank6.png' width=49 height=49 style='margin-top:-100%;margin-bottom:-100%;'\/>", "rating":1050, "alias":"shaddow", "ratingdelta":-4, "rank":78, "activity":1047, "score":1048}, {"emblem":"<img src='https:\/\/github.com\/GalconElim\/elim_rankings\/raw\/master\/rank6.png' width=49 height=49 style='margin-top:-100%;margin-bottom:-100%;'\/>", "rating":1049, "alias":"Fire.n.Ice.", "ratingdelta":0, "rank":79, "activity":233, "score":1047}, {"emblem":"<img src='https:\/\/github.com\/GalconElim\/elim_rankings\/raw\/master\/rank6.png' width=49 height=49 style='margin-top:-100%;margin-bottom:-100%;'\/>", "rating":1049, "alias":"bot", "ratingdelta":"+17", "rank":80, "activity":12656, "score":1044}, {"emblem":"<img src='https:\/\/github.com\/GalconElim\/elim_rankings\/raw\/master\/rank6.png' width=49 height=49 style='margin-top:-100%;margin-bottom:-100%;'\/>", "rating":1046, "alias":"stuggidavid", "ratingdelta":0, "rank":81, "activity":104, "score":1028}, {"emblem":"<img src='https:\/\/github.com\/GalconElim\/elim_rankings\/raw\/master\/rank6.png' width=49 height=49 style='margin-top:-100%;margin-bottom:-100%;'\/>", "rating":1042, "alias":"ATN", "ratingdelta":-2, "rank":82, "activity":396, "score":1004}, {"emblem":"<img src='https:\/\/github.com\/GalconElim\/elim_rankings\/raw\/master\/rank5.png' width=49 height=49 style='margin-top:-100%;margin-bottom:-100%;'\/>", "rating":1041, "alias":"QuickFlute~539", "ratingdelta":0, "rank":83, "activity":154, "score":1000}, {"emblem":"<img src='https:\/\/github.com\/GalconElim\/elim_rankings\/raw\/master\/rank5.png' width=49 height=49 style='margin-top:-100%;margin-bottom:-100%;'\/>", "rating":1041, "alias":"LJpain", "ratingdelta":0, "rank":84, "activity":169, "score":997}, {"emblem":"<img src='https:\/\/github.com\/GalconElim\/elim_rankings\/raw\/master\/rank5.png' width=49 height=49 style='margin-top:-100%;margin-bottom:-100%;'\/>", "rating":1040, "alias":"xpedient", "ratingdelta":0, "rank":85, "activity":311, "score":991}, {"emblem":"<img src='https:\/\/github.com\/GalconElim\/elim_rankings\/raw\/master\/rank5.png' width=49 height=49 style='margin-top:-100%;margin-bottom:-100%;'\/>", "rating":1036, "alias":"TheMainEvent", "ratingdelta":0, "rank":86, "activity":144, "score":969}, {"emblem":"<img src='https:\/\/github.com\/GalconElim\/elim_rankings\/raw\/master\/rank5.png' width=49 height=49 style='margin-top:-100%;margin-bottom:-100%;'\/>", "rating":1035, "alias":"BigTemper~185", "ratingdelta":0, "rank":87, "activity":108, "score":966}, {"emblem":"<img src='https:\/\/github.com\/GalconElim\/elim_rankings\/raw\/master\/rank5.png' width=49 height=49 style='margin-top:-100%;margin-bottom:-100%;'\/>", "rating":1035, "alias":"Meep", "ratingdelta":0, "rank":88, "activity":254, "score":965}, {"emblem":"<img src='https:\/\/github.com\/GalconElim\/elim_rankings\/raw\/master\/rank5.png' width=49 height=49 style='margin-top:-100%;margin-bottom:-100%;'\/>", "rating":1031, "alias":"AZ123", "ratingdelta":0, "rank":89, "activity":93, "score":940}, {"emblem":"<img src='https:\/\/github.com\/GalconElim\/elim_rankings\/raw\/master\/rank5.png' width=49 height=49 style='margin-top:-100%;margin-bottom:-100%;'\/>", "rating":1030, "alias":"AmusedGrill~659", "ratingdelta":"+2", "rank":90, "activity":436, "score":936}, {"emblem":"<img src='https:\/\/github.com\/GalconElim\/elim_rankings\/raw\/master\/rank5.png' width=49 height=49 style='margin-top:-100%;margin-bottom:-100%;'\/>", "rating":1030, "alias":"Vergilious", "ratingdelta":"+4", "rank":91, "activity":168, "score":934}, {"emblem":"<img src='https:\/\/github.com\/GalconElim\/elim_rankings\/raw\/master\/rank5.png' width=49 height=49 style='margin-top:-100%;margin-bottom:-100%;'\/>", "rating":1029, "alias":"babymetal", "ratingdelta":0, "rank":92, "activity":88, "score":933}, {"emblem":"<img src='https:\/\/github.com\/GalconElim\/elim_rankings\/raw\/master\/rank5.png' width=49 height=49 style='margin-top:-100%;margin-bottom:-100%;'\/>", "rating":1028, "alias":"penetration", "ratingdelta":0, "rank":93, "activity":238, "score":928}, {"emblem":"<img src='https:\/\/github.com\/GalconElim\/elim_rankings\/raw\/master\/rank5.png' width=49 height=49 style='margin-top:-100%;margin-bottom:-100%;'\/>", "rating":1028, "alias":"edache22", "ratingdelta":0, "rank":94, "activity":1640, "score":924}, {"emblem":"<img src='https:\/\/github.com\/GalconElim\/elim_rankings\/raw\/master\/rank5.png' width=49 height=49 style='margin-top:-100%;margin-bottom:-100%;'\/>", "rating":1027, "alias":"CrazyVest~284", "ratingdelta":"+3", "rank":95, "activity":130, "score":922}, {"emblem":"<img src='https:\/\/github.com\/GalconElim\/elim_rankings\/raw\/master\/rank5.png' width=49 height=49 style='margin-top:-100%;margin-bottom:-100%;'\/>", "rating":1027, "alias":"Infatuation-", "ratingdelta":0, "rank":96, "activity":139, "score":921}, {"emblem":"<img src='https:\/\/github.com\/GalconElim\/elim_rankings\/raw\/master\/rank5.png' width=49 height=49 style='margin-top:-100%;margin-bottom:-100%;'\/>", "rating":1027, "alias":"quantum", "ratingdelta":-1, "rank":97, "activity":524, "score":921}, {"emblem":"<img src='https:\/\/github.com\/GalconElim\/elim_rankings\/raw\/master\/rank5.png' width=49 height=49 style='margin-top:-100%;margin-bottom:-100%;'\/>", "rating":1026, "alias":"spamo", "ratingdelta":-1, "rank":98, "activity":542, "score":917}, {"emblem":"<img src='https:\/\/github.com\/GalconElim\/elim_rankings\/raw\/master\/rank5.png' width=49 height=49 style='margin-top:-100%;margin-bottom:-100%;'\/>", "rating":1026, "alias":"WanderLust20", "ratingdelta":0, "rank":99, "activity":945, "score":916}, {"emblem":"<img src='https:\/\/github.com\/GalconElim\/elim_rankings\/raw\/master\/rank5.png' width=49 height=49 style='margin-top:-100%;margin-bottom:-100%;'\/>", "rating":1026, "alias":"hyoshy", "ratingdelta":-4, "rank":100, "activity":159, "score":915}, {"emblem":"<img src='https:\/\/github.com\/GalconElim\/elim_rankings\/raw\/master\/rank5.png' width=49 height=49 style='margin-top:-100%;margin-bottom:-100%;'\/>", "rating":1026, "alias":"Blu.", "ratingdelta":"+9", "rank":101, "activity":188, "score":913}, {"emblem":"<img src='https:\/\/github.com\/GalconElim\/elim_rankings\/raw\/master\/rank5.png' width=49 height=49 style='margin-top:-100%;margin-bottom:-100%;'\/>", "rating":1025, "alias":"oPs_0ps", "ratingdelta":0, "rank":102, "activity":88, "score":912}, {"emblem":"<img src='https:\/\/github.com\/GalconElim\/elim_rankings\/raw\/master\/rank5.png' width=49 height=49 style='margin-top:-100%;margin-bottom:-100%;'\/>", "rating":1025, "alias":"Snake1976", "ratingdelta":-3, "rank":103, "activity":702, "score":910}, {"emblem":"<img src='https:\/\/github.com\/GalconElim\/elim_rankings\/raw\/master\/rank5.png' width=49 height=49 style='margin-top:-100%;margin-bottom:-100%;'\/>", "rating":1025, "alias":"monsterV", "ratingdelta":0, "rank":104, "activity":68, "score":909}, {"emblem":"<img src='https:\/\/github.com\/GalconElim\/elim_rankings\/raw\/master\/rank5.png' width=49 height=49 style='margin-top:-100%;margin-bottom:-100%;'\/>", "rating":1025, "alias":"malquee", "ratingdelta":0, "rank":105, "activity":58, "score":908}, {"emblem":"<img src='https:\/\/github.com\/GalconElim\/elim_rankings\/raw\/master\/rank5.png' width=49 height=49 style='margin-top:-100%;margin-bottom:-100%;'\/>", "rating":1024, "alias":"sjehsan", "ratingdelta":-5, "rank":106, "activity":568, "score":904}, {"emblem":"<img src='https:\/\/github.com\/GalconElim\/elim_rankings\/raw\/master\/rank5.png' width=49 height=49 style='margin-top:-100%;margin-bottom:-100%;'\/>", "rating":1024, "alias":"Rawz", "ratingdelta":"+3", "rank":107, "activity":58, "score":904}, {"emblem":"<img src='https:\/\/github.com\/GalconElim\/elim_rankings\/raw\/master\/rank5.png' width=49 height=49 style='margin-top:-100%;margin-bottom:-100%;'\/>", "rating":1023, "alias":"Flash640k", "ratingdelta":0, "rank":108, "activity":59, "score":897}, {"emblem":"<img src='https:\/\/github.com\/GalconElim\/elim_rankings\/raw\/master\/rank5.png' width=49 height=49 style='margin-top:-100%;margin-bottom:-100%;'\/>", "rating":1022, "alias":"Steve.Jobs", "ratingdelta":0, "rank":109, "activity":158, "score":893}, {"emblem":"<img src='https:\/\/github.com\/GalconElim\/elim_rankings\/raw\/master\/rank5.png' width=49 height=49 style='margin-top:-100%;margin-bottom:-100%;'\/>", "rating":1021, "alias":"thorack", "ratingdelta":-2, "rank":110, "activity":51, "score":890}, {"emblem":"<img src='https:\/\/github.com\/GalconElim\/elim_rankings\/raw\/master\/rank5.png' width=49 height=49 style='margin-top:-100%;margin-bottom:-100%;'\/>", "rating":1021, "alias":"flippant55", "ratingdelta":0, "rank":111, "activity":121, "score":888}, {"emblem":"<img src='https:\/\/github.com\/GalconElim\/elim_rankings\/raw\/master\/rank5.png' width=49 height=49 style='margin-top:-100%;margin-bottom:-100%;'\/>", "rating":1021, "alias":"hiasele", "ratingdelta":-2, "rank":112, "activity":142, "score":888}, {"emblem":"<img src='https:\/\/github.com\/GalconElim\/elim_rankings\/raw\/master\/rank5.png' width=49 height=49 style='margin-top:-100%;margin-bottom:-100%;'\/>", "rating":1020, "alias":"duruti", "ratingdelta":0, "rank":113, "activity":485, "score":887}, {"emblem":"<img src='https:\/\/github.com\/GalconElim\/elim_rankings\/raw\/master\/rank5.png' width=49 height=49 style='margin-top:-100%;margin-bottom:-100%;'\/>", "rating":1020, "alias":"Trashed", "ratingdelta":0, "rank":114, "activity":100, "score":882}, {"emblem":"<img src='https:\/\/github.com\/GalconElim\/elim_rankings\/raw\/master\/rank5.png' width=49 height=49 style='margin-top:-100%;margin-bottom:-100%;'\/>", "rating":1018, "alias":"SweetTooth~619", "ratingdelta":0, "rank":115, "activity":129, "score":876}, {"emblem":"<img src='https:\/\/github.com\/GalconElim\/elim_rankings\/raw\/master\/rank5.png' width=49 height=49 style='margin-top:-100%;margin-bottom:-100%;'\/>", "rating":1017, "alias":"evilCherry2", "ratingdelta":0, "rank":116, "activity":50, "score":868}, {"emblem":"<img src='https:\/\/github.com\/GalconElim\/elim_rankings\/raw\/master\/rank5.png' width=49 height=49 style='margin-top:-100%;margin-bottom:-100%;'\/>", "rating":1017, "alias":"SweetPeach~177", "ratingdelta":"+4", "rank":117, "activity":416, "score":867}, {"emblem":"<img src='https:\/\/github.com\/GalconElim\/elim_rankings\/raw\/master\/rank5.png' width=49 height=49 style='margin-top:-100%;margin-bottom:-100%;'\/>", "rating":1016, "alias":"ru-51", "ratingdelta":-5, "rank":118, "activity":521, "score":866}, {"emblem":"<img src='https:\/\/github.com\/GalconElim\/elim_rankings\/raw\/master\/rank5.png' width=49 height=49 style='margin-top:-100%;margin-bottom:-100%;'\/>", "rating":1016, "alias":"PaperGoose~533", "ratingdelta":0, "rank":119, "activity":162, "score":866}, {"emblem":"<img src='https:\/\/github.com\/GalconElim\/elim_rankings\/raw\/master\/rank5.png' width=49 height=49 style='margin-top:-100%;margin-bottom:-100%;'\/>", "rating":1014, "alias":"Snech", "ratingdelta":0, "rank":120, "activity":34, "score":856}, {"emblem":"<img src='https:\/\/github.com\/GalconElim\/elim_rankings\/raw\/master\/rank5.png' width=49 height=49 style='margin-top:-100%;margin-bottom:-100%;'\/>", "rating":1014, "alias":"number1daddy", "ratingdelta":"+1", "rank":121, "activity":77, "score":852}, {"emblem":"<img src='https:\/\/github.com\/GalconElim\/elim_rankings\/raw\/master\/rank5.png' width=49 height=49 style='margin-top:-100%;margin-bottom:-100%;'\/>", "rating":1014, "alias":"blankedout", "ratingdelta":-2, "rank":122, "activity":117, "score":852}, {"emblem":"<img src='https:\/\/github.com\/GalconElim\/elim_rankings\/raw\/master\/rank5.png' width=49 height=49 style='margin-top:-100%;margin-bottom:-100%;'\/>", "rating":1013, "alias":"Mangudai", "ratingdelta":0, "rank":123, "activity":20, "score":850}, {"emblem":"<img src='https:\/\/github.com\/GalconElim\/elim_rankings\/raw\/master\/rank5.png' width=49 height=49 style='margin-top:-100%;margin-bottom:-100%;'\/>", "rating":1013, "alias":"Vato96", "ratingdelta":"+3", "rank":124, "activity":292, "score":848}, {"emblem":"<img src='https:\/\/github.com\/GalconElim\/elim_rankings\/raw\/master\/rank5.png' width=49 height=49 style='margin-top:-100%;margin-bottom:-100%;'\/>", "rating":1011, "alias":"ganjasslol", "ratingdelta":0, "rank":125, "activity":178, "score":841}, {"emblem":"<img src='https:\/\/github.com\/GalconElim\/elim_rankings\/raw\/master\/rank4.png' width=49 height=49 style='margin-top:-100%;margin-bottom:-100%;'\/>", "rating":1011, "alias":"WindyMit~547", "ratingdelta":0, "rank":126, "activity":71, "score":839}, {"emblem":"<img src='https:\/\/github.com\/GalconElim\/elim_rankings\/raw\/master\/rank4.png' width=49 height=49 style='margin-top:-100%;margin-bottom:-100%;'\/>", "rating":1011, "alias":"mucker2.0", "ratingdelta":0, "rank":127, "activity":321, "score":838}, {"emblem":"<img src='https:\/\/github.com\/GalconElim\/elim_rankings\/raw\/master\/rank4.png' width=49 height=49 style='margin-top:-100%;margin-bottom:-100%;'\/>", "rating":1010, "alias":"SOfa_kingDOM", "ratingdelta":0, "rank":128, "activity":71, "score":837}, {"emblem":"<img src='https:\/\/github.com\/GalconElim\/elim_rankings\/raw\/master\/rank4.png' width=49 height=49 style='margin-top:-100%;margin-bottom:-100%;'\/>", "rating":1010, "alias":"thedude", "ratingdelta":0, "rank":129, "activity":123, "score":836}, {"emblem":"<img src='https:\/\/github.com\/GalconElim\/elim_rankings\/raw\/master\/rank4.png' width=49 height=49 style='margin-top:-100%;margin-bottom:-100%;'\/>", "rating":1010, "alias":"thestallion", "ratingdelta":0, "rank":130, "activity":164, "score":835}, {"emblem":"<img src='https:\/\/github.com\/GalconElim\/elim_rankings\/raw\/master\/rank4.png' width=49 height=49 style='margin-top:-100%;margin-bottom:-100%;'\/>", "rating":1010, "alias":"Ice.cream", "ratingdelta":0, "rank":131, "activity":76, "score":834}, {"emblem":"<img src='https:\/\/github.com\/GalconElim\/elim_rankings\/raw\/master\/rank4.png' width=49 height=49 style='margin-top:-100%;margin-bottom:-100%;'\/>", "rating":1009, "alias":"GreasyFang~961", "ratingdelta":0, "rank":132, "activity":134, "score":829}, {"emblem":"<img src='https:\/\/github.com\/GalconElim\/elim_rankings\/raw\/master\/rank4.png' width=49 height=49 style='margin-top:-100%;margin-bottom:-100%;'\/>", "rating":1009, "alias":"FinalFantasy", "ratingdelta":0, "rank":133, "activity":56, "score":828}, {"emblem":"<img src='https:\/\/github.com\/GalconElim\/elim_rankings\/raw\/master\/rank4.png' width=49 height=49 style='margin-top:-100%;margin-bottom:-100%;'\/>", "rating":1008, "alias":"SloppyTea~932", "ratingdelta":0, "rank":134, "activity":145, "score":824}, {"emblem":"<img src='https:\/\/github.com\/GalconElim\/elim_rankings\/raw\/master\/rank4.png' width=49 height=49 style='margin-top:-100%;margin-bottom:-100%;'\/>", "rating":1007, "alias":"BepoHuka", "ratingdelta":0, "rank":135, "activity":78, "score":823}, {"emblem":"<img src='https:\/\/github.com\/GalconElim\/elim_rankings\/raw\/master\/rank4.png' width=49 height=49 style='margin-top:-100%;margin-bottom:-100%;'\/>", "rating":1007, "alias":"GrumpyTable~555", "ratingdelta":0, "rank":136, "activity":228, "score":822}, {"emblem":"<img src='https:\/\/github.com\/GalconElim\/elim_rankings\/raw\/master\/rank4.png' width=49 height=49 style='margin-top:-100%;margin-bottom:-100%;'\/>", "rating":1005, "alias":"kaborage", "ratingdelta":-1, "rank":137, "activity":745, "score":809}, {"emblem":"<img src='https:\/\/github.com\/GalconElim\/elim_rankings\/raw\/master\/rank4.png' width=49 height=49 style='margin-top:-100%;margin-bottom:-100%;'\/>", "rating":1004, "alias":"SUPREME--", "ratingdelta":-1, "rank":138, "activity":119, "score":809}, {"emblem":"<img src='https:\/\/github.com\/GalconElim\/elim_rankings\/raw\/master\/rank4.png' width=49 height=49 style='margin-top:-100%;margin-bottom:-100%;'\/>", "rating":1004, "alias":"Bi-Polar", "ratingdelta":"+5", "rank":139, "activity":111, "score":807}, {"emblem":"<img src='https:\/\/github.com\/GalconElim\/elim_rankings\/raw\/master\/rank4.png' width=49 height=49 style='margin-top:-100%;margin-bottom:-100%;'\/>", "rating":1004, "alias":"SnappyWease~738", "ratingdelta":0, "rank":140, "activity":77, "score":806}, {"emblem":"<img src='https:\/\/github.com\/GalconElim\/elim_rankings\/raw\/master\/rank4.png' width=49 height=49 style='margin-top:-100%;margin-bottom:-100%;'\/>", "rating":1004, "alias":"Andy65536", "ratingdelta":0, "rank":141, "activity":267, "score":806}, {"emblem":"<img src='https:\/\/github.com\/GalconElim\/elim_rankings\/raw\/master\/rank4.png' width=49 height=49 style='margin-top:-100%;margin-bottom:-100%;'\/>", "rating":1004, "alias":"Fruitfox", "ratingdelta":0, "rank":142, "activity":194, "score":804}, {"emblem":"<img src='https:\/\/github.com\/GalconElim\/elim_rankings\/raw\/master\/rank4.png' width=49 height=49 style='margin-top:-100%;margin-bottom:-100%;'\/>", "rating":1003, "alias":"Geromyty", "ratingdelta":"+8", "rank":143, "activity":135, "score":803}, {"emblem":"<img src='https:\/\/github.com\/GalconElim\/elim_rankings\/raw\/master\/rank4.png' width=49 height=49 style='margin-top:-100%;margin-bottom:-100%;'\/>", "rating":1003, "alias":"Glossy", "ratingdelta":"+3", "rank":144, "activity":621, "score":802}, {"emblem":"<img src='https:\/\/github.com\/GalconElim\/elim_rankings\/raw\/master\/rank4.png' width=49 height=49 style='margin-top:-100%;margin-bottom:-100%;'\/>", "rating":1002, "alias":"Desperation", "ratingdelta":0, "rank":145, "activity":42, "score":799}, {"emblem":"<img src='https:\/\/github.com\/GalconElim\/elim_rankings\/raw\/master\/rank4.png' width=49 height=49 style='margin-top:-100%;margin-bottom:-100%;'\/>", "rating":1002, "alias":"Jake125", "ratingdelta":0, "rank":146, "activity":65, "score":799}, {"emblem":"<img src='https:\/\/github.com\/GalconElim\/elim_rankings\/raw\/master\/rank4.png' width=49 height=49 style='margin-top:-100%;margin-bottom:-100%;'\/>", "rating":1002, "alias":"PursuitOfPow", "ratingdelta":-5, "rank":147, "activity":493, "score":797}, {"emblem":"<img src='https:\/\/github.com\/GalconElim\/elim_rankings\/raw\/master\/rank4.png' width=49 height=49 style='margin-top:-100%;margin-bottom:-100%;'\/>", "rating":1002, "alias":"batman7000", "ratingdelta":-2, "rank":148, "activity":135, "score":797}, {"emblem":"<img src='https:\/\/github.com\/GalconElim\/elim_rankings\/raw\/master\/rank4.png' width=49 height=49 style='margin-top:-100%;margin-bottom:-100%;'\/>", "rating":1002, "alias":"sofierce", "ratingdelta":-1, "rank":149, "activity":64, "score":796}, {"emblem":"<img src='https:\/\/github.com\/GalconElim\/elim_rankings\/raw\/master\/rank4.png' width=49 height=49 style='margin-top:-100%;margin-bottom:-100%;'\/>", "rating":1002, "alias":"playin4keeps", "ratingdelta":0, "rank":150, "activity":164, "score":795}, {"emblem":"<img src='https:\/\/github.com\/GalconElim\/elim_rankings\/raw\/master\/rank4.png' width=49 height=49 style='margin-top:-100%;margin-bottom:-100%;'\/>", "rating":1001, "alias":"Fanfoue9", "ratingdelta":-1, "rank":151, "activity":72, "score":794}, {"emblem":"<img src='https:\/\/github.com\/GalconElim\/elim_rankings\/raw\/master\/rank4.png' width=49 height=49 style='margin-top:-100%;margin-bottom:-100%;'\/>", "rating":1001, "alias":"RipePossum~959", "ratingdelta":0, "rank":152, "activity":57, "score":791}, {"emblem":"<img src='https:\/\/github.com\/GalconElim\/elim_rankings\/raw\/master\/rank4.png' width=49 height=49 style='margin-top:-100%;margin-bottom:-100%;'\/>", "rating":1000, "alias":"SparkyPlane", "ratingdelta":-4, "rank":153, "activity":68, "score":790}, {"emblem":"<img src='https:\/\/github.com\/GalconElim\/elim_rankings\/raw\/master\/rank4.png' width=49 height=49 style='margin-top:-100%;margin-bottom:-100%;'\/>", "rating":1000, "alias":"timogen", "ratingdelta":"+1", "rank":154, "activity":101, "score":787}, {"emblem":"<img src='https:\/\/github.com\/GalconElim\/elim_rankings\/raw\/master\/rank4.png' width=49 height=49 style='margin-top:-100%;margin-bottom:-100%;'\/>", "rating":999, "alias":"HollowHoppe~374", "ratingdelta":0, "rank":155, "activity":40, "score":786}, {"emblem":"<img src='https:\/\/github.com\/GalconElim\/elim_rankings\/raw\/master\/rank4.png' width=49 height=49 style='margin-top:-100%;margin-bottom:-100%;'\/>", "rating":999, "alias":"JuicyBread~414", "ratingdelta":0, "rank":156, "activity":96, "score":785}, {"emblem":"<img src='https:\/\/github.com\/GalconElim\/elim_rankings\/raw\/master\/rank4.png' width=49 height=49 style='margin-top:-100%;margin-bottom:-100%;'\/>", "rating":999, "alias":"YoYo_XCA", "ratingdelta":0, "rank":157, "activity":86, "score":785}, {"emblem":"<img src='https:\/\/github.com\/GalconElim\/elim_rankings\/raw\/master\/rank4.png' width=49 height=49 style='margin-top:-100%;margin-bottom:-100%;'\/>", "rating":999, "alias":"LiquidSock~186", "ratingdelta":0, "rank":158, "activity":111, "score":785}, {"emblem":"<img src='https:\/\/github.com\/GalconElim\/elim_rankings\/raw\/master\/rank4.png' width=49 height=49 style='margin-top:-100%;margin-bottom:-100%;'\/>", "rating":999, "alias":"FilthyGlide~918", "ratingdelta":0, "rank":159, "activity":56, "score":784}, {"emblem":"<img src='https:\/\/github.com\/GalconElim\/elim_rankings\/raw\/master\/rank4.png' width=49 height=49 style='margin-top:-100%;margin-bottom:-100%;'\/>", "rating":999, "alias":"VividerAphid", "ratingdelta":0, "rank":160, "activity":85, "score":783}, {"emblem":"<img src='https:\/\/github.com\/GalconElim\/elim_rankings\/raw\/master\/rank4.png' width=49 height=49 style='margin-top:-100%;margin-bottom:-100%;'\/>", "rating":999, "alias":"SilkyBlur~664", "ratingdelta":"+5", "rank":161, "activity":262, "score":783}, {"emblem":"<img src='https:\/\/github.com\/GalconElim\/elim_rankings\/raw\/master\/rank4.png' width=49 height=49 style='margin-top:-100%;margin-bottom:-100%;'\/>", "rating":999, "alias":"Jamesking135", "ratingdelta":-1, "rank":162, "activity":375, "score":782}, {"emblem":"<img src='https:\/\/github.com\/GalconElim\/elim_rankings\/raw\/master\/rank4.png' width=49 height=49 style='margin-top:-100%;margin-bottom:-100%;'\/>", "rating":998, "alias":"WPooh.Flute", "ratingdelta":0, "rank":163, "activity":35, "score":780}, {"emblem":"<img src='https:\/\/github.com\/GalconElim\/elim_rankings\/raw\/master\/rank4.png' width=49 height=49 style='margin-top:-100%;margin-bottom:-100%;'\/>", "rating":998, "alias":"Crims0n", "ratingdelta":0, "rank":164, "activity":31, "score":779}, {"emblem":"<img src='https:\/\/github.com\/GalconElim\/elim_rankings\/raw\/master\/rank4.png' width=49 height=49 style='margin-top:-100%;margin-bottom:-100%;'\/>", "rating":998, "alias":"Lunula", "ratingdelta":0, "rank":165, "activity":48, "score":778}, {"emblem":"<img src='https:\/\/github.com\/GalconElim\/elim_rankings\/raw\/master\/rank4.png' width=49 height=49 style='margin-top:-100%;margin-bottom:-100%;'\/>", "rating":998, "alias":"Joey125", "ratingdelta":0, "rank":166, "activity":40, "score":777}, {"emblem":"<img src='https:\/\/github.com\/GalconElim\/elim_rankings\/raw\/master\/rank4.png' width=49 height=49 style='margin-top:-100%;margin-bottom:-100%;'\/>", "rating":997, "alias":"MaBallsRFull", "ratingdelta":0, "rank":167, "activity":175, "score":776}, {"emblem":"<img src='https:\/\/github.com\/GalconElim\/elim_rankings\/raw\/master\/rank4.png' width=49 height=49 style='margin-top:-100%;margin-bottom:-100%;'\/>", "rating":997, "alias":"wibbs", "ratingdelta":-1, "rank":168, "activity":26, "score":776}, {"emblem":"<img src='https:\/\/github.com\/GalconElim\/elim_rankings\/raw\/master\/rank4.png' width=49 height=49 style='margin-top:-100%;margin-bottom:-100%;'\/>", "rating":997, "alias":"TinySound~597", "ratingdelta":0, "rank":169, "activity":35, "score":774}, {"emblem":"<img src='https:\/\/github.com\/GalconElim\/elim_rankings\/raw\/master\/rank4.png' width=49 height=49 style='margin-top:-100%;margin-bottom:-100%;'\/>", "rating":997, "alias":"Knightimer", "ratingdelta":-3, "rank":170, "activity":620, "score":773}, {"emblem":"<img src='https:\/\/github.com\/GalconElim\/elim_rankings\/raw\/master\/rank4.png' width=49 height=49 style='margin-top:-100%;margin-bottom:-100%;'\/>", "rating":997, "alias":"LoudSoup~240", "ratingdelta":0, "rank":171, "activity":70, "score":773}, {"emblem":"<img src='https:\/\/github.com\/GalconElim\/elim_rankings\/raw\/master\/rank4.png' width=49 height=49 style='margin-top:-100%;margin-bottom:-100%;'\/>", "rating":996, "alias":"Tscharee", "ratingdelta":"+4", "rank":172, "activity":189, "score":772}, {"emblem":"<img src='https:\/\/github.com\/GalconElim\/elim_rankings\/raw\/master\/rank4.png' width=49 height=49 style='margin-top:-100%;margin-bottom:-100%;'\/>", "rating":996, "alias":"sAmA", "ratingdelta":0, "rank":173, "activity":57, "score":771}, {"emblem":"<img src='https:\/\/github.com\/GalconElim\/elim_rankings\/raw\/master\/rank4.png' width=49 height=49 style='margin-top:-100%;margin-bottom:-100%;'\/>", "rating":996, "alias":"I..", "ratingdelta":0, "rank":174, "activity":25, "score":771}, {"emblem":"<img src='https:\/\/github.com\/GalconElim\/elim_rankings\/raw\/master\/rank4.png' width=49 height=49 style='margin-top:-100%;margin-bottom:-100%;'\/>", "rating":996, "alias":"Mutation-", "ratingdelta":0, "rank":175, "activity":117, "score":771}, {"emblem":"<img src='https:\/\/github.com\/GalconElim\/elim_rankings\/raw\/master\/rank4.png' width=49 height=49 style='margin-top:-100%;margin-bottom:-100%;'\/>", "rating":996, "alias":"cocoadog", "ratingdelta":-3, "rank":176, "activity":99, "score":769}, {"emblem":"<img src='https:\/\/github.com\/GalconElim\/elim_rankings\/raw\/master\/rank4.png' width=49 height=49 style='margin-top:-100%;margin-bottom:-100%;'\/>", "rating":995, "alias":"Alburdy", "ratingdelta":-1, "rank":177, "activity":783, "score":767}, {"emblem":"<img src='https:\/\/github.com\/GalconElim\/elim_rankings\/raw\/master\/rank4.png' width=49 height=49 style='margin-top:-100%;margin-bottom:-100%;'\/>", "rating":995, "alias":"xaelia", "ratingdelta":0, "rank":178, "activity":37, "score":765}, {"emblem":"<img src='https:\/\/github.com\/GalconElim\/elim_rankings\/raw\/master\/rank4.png' width=49 height=49 style='margin-top:-100%;margin-bottom:-100%;'\/>", "rating":995, "alias":"VNS700", "ratingdelta":-2, "rank":179, "activity":177, "score":764}, {"emblem":"<img src='https:\/\/github.com\/GalconElim\/elim_rankings\/raw\/master\/rank4.png' width=49 height=49 style='margin-top:-100%;margin-bottom:-100%;'\/>", "rating":994, "alias":"darth_jesse", "ratingdelta":0, "rank":180, "activity":90, "score":760}, {"emblem":"<img src='https:\/\/github.com\/GalconElim\/elim_rankings\/raw\/master\/rank4.png' width=49 height=49 style='margin-top:-100%;margin-bottom:-100%;'\/>", "rating":994, "alias":"chadbrochill", "ratingdelta":0, "rank":181, "activity":173, "score":760}, {"emblem":"<img src='https:\/\/github.com\/GalconElim\/elim_rankings\/raw\/master\/rank4.png' width=49 height=49 style='margin-top:-100%;margin-bottom:-100%;'\/>", "rating":994, "alias":"bandits22", "ratingdelta":"+1", "rank":182, "activity":34, "score":760}, {"emblem":"<img src='https:\/\/github.com\/GalconElim\/elim_rankings\/raw\/master\/rank4.png' width=49 height=49 style='margin-top:-100%;margin-bottom:-100%;'\/>", "rating":993, "alias":"Miniongalcon", "ratingdelta":-6, "rank":183, "activity":47, "score":757}, {"emblem":"<img src='https:\/\/github.com\/GalconElim\/elim_rankings\/raw\/master\/rank4.png' width=49 height=49 style='margin-top:-100%;margin-bottom:-100%;'\/>", "rating":993, "alias":"ElsaCaputas", "ratingdelta":0, "rank":184, "activity":95, "score":756}, {"emblem":"<img src='https:\/\/github.com\/GalconElim\/elim_rankings\/raw\/master\/rank4.png' width=49 height=49 style='margin-top:-100%;margin-bottom:-100%;'\/>", "rating":993, "alias":"RaggedZebra", "ratingdelta":0, "rank":185, "activity":102, "score":756}, {"emblem":"<img src='https:\/\/github.com\/GalconElim\/elim_rankings\/raw\/master\/rank4.png' width=49 height=49 style='margin-top:-100%;margin-bottom:-100%;'\/>", "rating":992, "alias":"CHAMPIONS", "ratingdelta":"+1", "rank":186, "activity":63, "score":754}, {"emblem":"<img src='https:\/\/github.com\/GalconElim\/elim_rankings\/raw\/master\/rank4.png' width=49 height=49 style='margin-top:-100%;margin-bottom:-100%;'\/>", "rating":992, "alias":"BigBabbaDope", "ratingdelta":0, "rank":187, "activity":157, "score":752}, {"emblem":"<img src='https:\/\/github.com\/GalconElim\/elim_rankings\/raw\/master\/rank4.png' width=49 height=49 style='margin-top:-100%;margin-bottom:-100%;'\/>", "rating":992, "alias":"comandar", "ratingdelta":"+1", "rank":188, "activity":148, "score":751}, {"emblem":"<img src='https:\/\/github.com\/GalconElim\/elim_rankings\/raw\/master\/rank4.png' width=49 height=49 style='margin-top:-100%;margin-bottom:-100%;'\/>", "rating":991, "alias":"laviathon", "ratingdelta":0, "rank":189, "activity":150, "score":749}, {"emblem":"<img src='https:\/\/github.com\/GalconElim\/elim_rankings\/raw\/master\/rank4.png' width=49 height=49 style='margin-top:-100%;margin-bottom:-100%;'\/>", "rating":990, "alias":"rpk", "ratingdelta":0, "rank":190, "activity":44, "score":746}, {"emblem":"<img src='https:\/\/github.com\/GalconElim\/elim_rankings\/raw\/master\/rank4.png' width=49 height=49 style='margin-top:-100%;margin-bottom:-100%;'\/>", "rating":990, "alias":"BouncyToast~533", "ratingdelta":0, "rank":191, "activity":105, "score":745}, {"emblem":"<img src='https:\/\/github.com\/GalconElim\/elim_rankings\/raw\/master\/rank4.png' width=49 height=49 style='margin-top:-100%;margin-bottom:-100%;'\/>", "rating":990, "alias":"VOSTOK", "ratingdelta":0, "rank":192, "activity":142, "score":744}, {"emblem":"<img src='https:\/\/github.com\/GalconElim\/elim_rankings\/raw\/master\/rank4.png' width=49 height=49 style='margin-top:-100%;margin-bottom:-100%;'\/>", "rating":990, "alias":"Ammin", "ratingdelta":-1, "rank":193, "activity":93, "score":742}, {"emblem":"<img src='https:\/\/github.com\/GalconElim\/elim_rankings\/raw\/master\/rank4.png' width=49 height=49 style='margin-top:-100%;margin-bottom:-100%;'\/>", "rating":989, "alias":"katy.cat", "ratingdelta":-6, "rank":194, "activity":48, "score":739}, {"emblem":"<img src='https:\/\/github.com\/GalconElim\/elim_rankings\/raw\/master\/rank4.png' width=49 height=49 style='margin-top:-100%;margin-bottom:-100%;'\/>", "rating":988, "alias":"phantomplan", "ratingdelta":0, "rank":195, "activity":175, "score":738}, {"emblem":"<img src='https:\/\/github.com\/GalconElim\/elim_rankings\/raw\/master\/rank4.png' width=49 height=49 style='margin-top:-100%;margin-bottom:-100%;'\/>", "rating":988, "alias":"SappyBlur", "ratingdelta":0, "rank":196, "activity":33, "score":736}, {"emblem":"<img src='https:\/\/github.com\/GalconElim\/elim_rankings\/raw\/master\/rank4.png' width=49 height=49 style='margin-top:-100%;margin-bottom:-100%;'\/>", "rating":988, "alias":"HAIDER99", "ratingdelta":0, "rank":197, "activity":61, "score":734}, {"emblem":"<img src='https:\/\/github.com\/GalconElim\/elim_rankings\/raw\/master\/rank4.png' width=49 height=49 style='margin-top:-100%;margin-bottom:-100%;'\/>", "rating":987, "alias":"marcsync", "ratingdelta":"+12", "rank":198, "activity":424, "score":731}, {"emblem":"<img src='https:\/\/github.com\/GalconElim\/elim_rankings\/raw\/master\/rank4.png' width=49 height=49 style='margin-top:-100%;margin-bottom:-100%;'\/>", "rating":987, "alias":"HTALAQI", "ratingdelta":"+3", "rank":199, "activity":131, "score":731}, {"emblem":"<img src='https:\/\/github.com\/GalconElim\/elim_rankings\/raw\/master\/rank4.png' width=49 height=49 style='margin-top:-100%;margin-bottom:-100%;'\/>", "rating":986, "alias":"Nimsta", "ratingdelta":"+5", "rank":200, "activity":282, "score":728}, {"emblem":"<img src='https:\/\/github.com\/GalconElim\/elim_rankings\/raw\/master\/rank4.png' width=49 height=49 style='margin-top:-100%;margin-bottom:-100%;'\/>", "rating":985, "alias":"zintencityp", "ratingdelta":-3, "rank":201, "activity":57, "score":725}, {"emblem":"<img src='https:\/\/github.com\/GalconElim\/elim_rankings\/raw\/master\/rank4.png' width=49 height=49 style='margin-top:-100%;margin-bottom:-100%;'\/>", "rating":985, "alias":"ciubaka", "ratingdelta":0, "rank":202, "activity":51, "score":721}, {"emblem":"<img src='https:\/\/github.com\/GalconElim\/elim_rankings\/raw\/master\/rank4.png' width=49 height=49 style='margin-top:-100%;margin-bottom:-100%;'\/>", "rating":985, "alias":"azi_dahaka", "ratingdelta":0, "rank":203, "activity":33, "score":721}, {"emblem":"<img src='https:\/\/github.com\/GalconElim\/elim_rankings\/raw\/master\/rank4.png' width=49 height=49 style='margin-top:-100%;margin-bottom:-100%;'\/>", "rating":982, "alias":"boww38", "ratingdelta":-3, "rank":204, "activity":125, "score":712}, {"emblem":"<img src='https:\/\/github.com\/GalconElim\/elim_rankings\/raw\/master\/rank4.png' width=49 height=49 style='margin-top:-100%;margin-bottom:-100%;'\/>", "rating":982, "alias":"BigUU", "ratingdelta":0, "rank":205, "activity":620, "score":711}, {"emblem":"<img src='https:\/\/github.com\/GalconElim\/elim_rankings\/raw\/master\/rank4.png' width=49 height=49 style='margin-top:-100%;margin-bottom:-100%;'\/>", "rating":982, "alias":"murilobg", "ratingdelta":0, "rank":206, "activity":130, "score":710}, {"emblem":"<img src='https:\/\/github.com\/GalconElim\/elim_rankings\/raw\/master\/rank3.png' width=49 height=49 style='margin-top:-100%;margin-bottom:-100%;'\/>", "rating":980, "alias":"pawwolf", "ratingdelta":"+1", "rank":207, "activity":121, "score":704}, {"emblem":"<img src='https:\/\/github.com\/GalconElim\/elim_rankings\/raw\/master\/rank3.png' width=49 height=49 style='margin-top:-100%;margin-bottom:-100%;'\/>", "rating":980, "alias":"bandy", "ratingdelta":0, "rank":208, "activity":134, "score":703}, {"emblem":"<img src='https:\/\/github.com\/GalconElim\/elim_rankings\/raw\/master\/rank3.png' width=49 height=49 style='margin-top:-100%;margin-bottom:-100%;'\/>", "rating":980, "alias":"mthomas76", "ratingdelta":0, "rank":209, "activity":78, "score":701}, {"emblem":"<img src='https:\/\/github.com\/GalconElim\/elim_rankings\/raw\/master\/rank3.png' width=49 height=49 style='margin-top:-100%;margin-bottom:-100%;'\/>", "rating":979, "alias":"SpicyViper", "ratingdelta":-1, "rank":210, "activity":241, "score":698}, {"emblem":"<img src='https:\/\/github.com\/GalconElim\/elim_rankings\/raw\/master\/rank3.png' width=49 height=49 style='margin-top:-100%;margin-bottom:-100%;'\/>", "rating":979, "alias":"FuzzyHam~452", "ratingdelta":0, "rank":211, "activity":1067, "score":697}, {"emblem":"<img src='https:\/\/github.com\/GalconElim\/elim_rankings\/raw\/master\/rank3.png' width=49 height=49 style='margin-top:-100%;margin-bottom:-100%;'\/>", "rating":978, "alias":"resistfate88", "ratingdelta":-1, "rank":212, "activity":75, "score":696}, {"emblem":"<img src='https:\/\/github.com\/GalconElim\/elim_rankings\/raw\/master\/rank3.png' width=49 height=49 style='margin-top:-100%;margin-bottom:-100%;'\/>", "rating":976, "alias":"GenBelIblis", "ratingdelta":0, "rank":213, "activity":331, "score":686}, {"emblem":"<img src='https:\/\/github.com\/GalconElim\/elim_rankings\/raw\/master\/rank3.png' width=49 height=49 style='margin-top:-100%;margin-bottom:-100%;'\/>", "rating":976, "alias":"enzokpo123", "ratingdelta":0, "rank":214, "activity":56, "score":685}, {"emblem":"<img src='https:\/\/github.com\/GalconElim\/elim_rankings\/raw\/master\/rank3.png' width=49 height=49 style='margin-top:-100%;margin-bottom:-100%;'\/>", "rating":975, "alias":"florihupf", "ratingdelta":0, "rank":215, "activity":42, "score":681}, {"emblem":"<img src='https:\/\/github.com\/GalconElim\/elim_rankings\/raw\/master\/rank3.png' width=49 height=49 style='margin-top:-100%;margin-bottom:-100%;'\/>", "rating":974, "alias":"nazia13", "ratingdelta":"+2", "rank":216, "activity":125, "score":680}, {"emblem":"<img src='https:\/\/github.com\/GalconElim\/elim_rankings\/raw\/master\/rank3.png' width=49 height=49 style='margin-top:-100%;margin-bottom:-100%;'\/>", "rating":974, "alias":"BigHuggie", "ratingdelta":0, "rank":217, "activity":51, "score":679}, {"emblem":"<img src='https:\/\/github.com\/GalconElim\/elim_rankings\/raw\/master\/rank3.png' width=49 height=49 style='margin-top:-100%;margin-bottom:-100%;'\/>", "rating":973, "alias":"mae_1", "ratingdelta":-3, "rank":218, "activity":94, "score":674}, {"emblem":"<img src='https:\/\/github.com\/GalconElim\/elim_rankings\/raw\/master\/rank3.png' width=49 height=49 style='margin-top:-100%;margin-bottom:-100%;'\/>", "rating":972, "alias":"lexa96as", "ratingdelta":0, "rank":219, "activity":61, "score":670}, {"emblem":"<img src='https:\/\/github.com\/GalconElim\/elim_rankings\/raw\/master\/rank3.png' width=49 height=49 style='margin-top:-100%;margin-bottom:-100%;'\/>", "rating":971, "alias":"Pantythief", "ratingdelta":0, "rank":220, "activity":288, "score":668}, {"emblem":"<img src='https:\/\/github.com\/GalconElim\/elim_rankings\/raw\/master\/rank3.png' width=49 height=49 style='margin-top:-100%;margin-bottom:-100%;'\/>", "rating":971, "alias":"Ammar_N", "ratingdelta":"+1", "rank":221, "activity":54, "score":667}, {"emblem":"<img src='https:\/\/github.com\/GalconElim\/elim_rankings\/raw\/master\/rank3.png' width=49 height=49 style='margin-top:-100%;margin-bottom:-100%;'\/>", "rating":971, "alias":"lelofadel111", "ratingdelta":"+2", "rank":222, "activity":139, "score":666}, {"emblem":"<img src='https:\/\/github.com\/GalconElim\/elim_rankings\/raw\/master\/rank3.png' width=49 height=49 style='margin-top:-100%;margin-bottom:-100%;'\/>", "rating":969, "alias":"Viper715", "ratingdelta":"+3", "rank":223, "activity":344, "score":658}, {"emblem":"<img src='https:\/\/github.com\/GalconElim\/elim_rankings\/raw\/master\/rank3.png' width=49 height=49 style='margin-top:-100%;margin-bottom:-100%;'\/>", "rating":968, "alias":"LastTimeLord", "ratingdelta":"+4", "rank":224, "activity":952, "score":654}, {"emblem":"<img src='https:\/\/github.com\/GalconElim\/elim_rankings\/raw\/master\/rank3.png' width=49 height=49 style='margin-top:-100%;margin-bottom:-100%;'\/>", "rating":966, "alias":"ZincSheet~351", "ratingdelta":-3, "rank":225, "activity":191, "score":648}, {"emblem":"<img src='https:\/\/github.com\/GalconElim\/elim_rankings\/raw\/master\/rank3.png' width=49 height=49 style='margin-top:-100%;margin-bottom:-100%;'\/>", "rating":964, "alias":"MR_JABROT_X", "ratingdelta":-1, "rank":226, "activity":55, "score":642}, {"emblem":"<img src='https:\/\/github.com\/GalconElim\/elim_rankings\/raw\/master\/rank3.png' width=49 height=49 style='margin-top:-100%;margin-bottom:-100%;'\/>", "rating":964, "alias":"Blaigen", "ratingdelta":0, "rank":227, "activity":110, "score":641}, {"emblem":"<img src='https:\/\/github.com\/GalconElim\/elim_rankings\/raw\/master\/rank3.png' width=49 height=49 style='margin-top:-100%;margin-bottom:-100%;'\/>", "rating":964, "alias":"ShinyTemper~434", "ratingdelta":0, "rank":228, "activity":52, "score":641}, {"emblem":"<img src='https:\/\/github.com\/GalconElim\/elim_rankings\/raw\/master\/rank3.png' width=49 height=49 style='margin-top:-100%;margin-bottom:-100%;'\/>", "rating":961, "alias":"mashehu", "ratingdelta":"+1", "rank":229, "activity":490, "score":631}, {"emblem":"<img src='https:\/\/github.com\/GalconElim\/elim_rankings\/raw\/master\/rank3.png' width=49 height=49 style='margin-top:-100%;margin-bottom:-100%;'\/>", "rating":961, "alias":"locochon133", "ratingdelta":-2, "rank":230, "activity":85, "score":628}, {"emblem":"<img src='https:\/\/github.com\/GalconElim\/elim_rankings\/raw\/master\/rank3.png' width=49 height=49 style='margin-top:-100%;margin-bottom:-100%;'\/>", "rating":956, "alias":"mattymate", "ratingdelta":0, "rank":231, "activity":184, "score":613}, {"emblem":"<img src='https:\/\/github.com\/GalconElim\/elim_rankings\/raw\/master\/rank3.png' width=49 height=49 style='margin-top:-100%;margin-bottom:-100%;'\/>", "rating":956, "alias":"WickedDrago~460", "ratingdelta":0, "rank":232, "activity":304, "score":611}, {"emblem":"<img src='https:\/\/github.com\/GalconElim\/elim_rankings\/raw\/master\/rank3.png' width=49 height=49 style='margin-top:-100%;margin-bottom:-100%;'\/>", "rating":954, "alias":"phichi", "ratingdelta":0, "rank":233, "activity":277, "score":606}, {"emblem":"<img src='https:\/\/github.com\/GalconElim\/elim_rankings\/raw\/master\/rank3.png' width=49 height=49 style='margin-top:-100%;margin-bottom:-100%;'\/>", "rating":954, "alias":"moofaffa4", "ratingdelta":0, "rank":234, "activity":47, "score":605}, {"emblem":"<img src='https:\/\/github.com\/GalconElim\/elim_rankings\/raw\/master\/rank3.png' width=49 height=49 style='margin-top:-100%;margin-bottom:-100%;'\/>", "rating":952, "alias":"BurlyWheel~628", "ratingdelta":0, "rank":235, "activity":224, "score":598}, {"emblem":"<img src='https:\/\/github.com\/GalconElim\/elim_rankings\/raw\/master\/rank2.png' width=49 height=49 style='margin-top:-100%;margin-bottom:-100%;'\/>", "rating":951, "alias":"gervi", "ratingdelta":"+2", "rank":236, "activity":380, "score":594}, {"emblem":"<img src='https:\/\/github.com\/GalconElim\/elim_rankings\/raw\/master\/rank2.png' width=49 height=49 style='margin-top:-100%;margin-bottom:-100%;'\/>", "rating":948, "alias":"FluffyBunny4", "ratingdelta":0, "rank":237, "activity":47, "score":584}, {"emblem":"<img src='https:\/\/github.com\/GalconElim\/elim_rankings\/raw\/master\/rank2.png' width=49 height=49 style='margin-top:-100%;margin-bottom:-100%;'\/>", "rating":945, "alias":"kern4life", "ratingdelta":-2, "rank":238, "activity":175, "score":574}, {"emblem":"<img src='https:\/\/github.com\/GalconElim\/elim_rankings\/raw\/master\/rank2.png' width=49 height=49 style='margin-top:-100%;margin-bottom:-100%;'\/>", "rating":945, "alias":"statenisland", "ratingdelta":-14, "rank":239, "activity":510, "score":573}, {"emblem":"<img src='https:\/\/github.com\/GalconElim\/elim_rankings\/raw\/master\/rank2.png' width=49 height=49 style='margin-top:-100%;margin-bottom:-100%;'\/>", "rating":944, "alias":"antv2", "ratingdelta":-1, "rank":240, "activity":255, "score":570}, {"emblem":"<img src='https:\/\/github.com\/GalconElim\/elim_rankings\/raw\/master\/rank2.png' width=49 height=49 style='margin-top:-100%;margin-bottom:-100%;'\/>", "rating":942, "alias":"newpoweR", "ratingdelta":-1, "rank":241, "activity":144, "score":565}, {"emblem":"<img src='https:\/\/github.com\/GalconElim\/elim_rankings\/raw\/master\/rank2.png' width=49 height=49 style='margin-top:-100%;margin-bottom:-100%;'\/>", "rating":940, "alias":"WateryApple~232", "ratingdelta":-1, "rank":242, "activity":152, "score":557}, {"emblem":"<img src='https:\/\/github.com\/GalconElim\/elim_rankings\/raw\/master\/rank2.png' width=49 height=49 style='margin-top:-100%;margin-bottom:-100%;'\/>", "rating":939, "alias":"Grimfandango", "ratingdelta":-3, "rank":243, "activity":115, "score":554}, {"emblem":"<img src='https:\/\/github.com\/GalconElim\/elim_rankings\/raw\/master\/rank2.png' width=49 height=49 style='margin-top:-100%;margin-bottom:-100%;'\/>", "rating":932, "alias":"cryp7", "ratingdelta":-2, "rank":244, "activity":555, "score":533}, {"emblem":"<img src='https:\/\/github.com\/GalconElim\/elim_rankings\/raw\/master\/rank2.png' width=49 height=49 style='margin-top:-100%;margin-bottom:-100%;'\/>", "rating":931, "alias":"panadool", "ratingdelta":0, "rank":245, "activity":137, "score":529}, {"emblem":"<img src='https:\/\/github.com\/GalconElim\/elim_rankings\/raw\/master\/rank2.png' width=49 height=49 style='margin-top:-100%;margin-bottom:-100%;'\/>", "rating":925, "alias":"justendit", "ratingdelta":0, "rank":246, "activity":333, "score":510}, {"emblem":"<img src='https:\/\/github.com\/GalconElim\/elim_rankings\/raw\/master\/rank2.png' width=49 height=49 style='margin-top:-100%;margin-bottom:-100%;'\/>", "rating":923, "alias":"wildhat-972", "ratingdelta":"+2", "rank":247, "activity":945, "score":505}, {"emblem":"<img src='https:\/\/github.com\/GalconElim\/elim_rankings\/raw\/master\/rank2.png' width=49 height=49 style='margin-top:-100%;margin-bottom:-100%;'\/>", "rating":922, "alias":"seoirse", "ratingdelta":"+1", "rank":248, "activity":69, "score":504}, {"emblem":"<img src='https:\/\/github.com\/GalconElim\/elim_rankings\/raw\/master\/rank1.png' width=49 height=49 style='margin-top:-100%;margin-bottom:-100%;'\/>", "rating":915, "alias":"unbridled", "ratingdelta":"+6", "rank":249, "activity":805, "score":483}, {"emblem":"<img src='https:\/\/github.com\/GalconElim\/elim_rankings\/raw\/master\/rank1.png' width=49 height=49 style='margin-top:-100%;margin-bottom:-100%;'\/>", "rating":904, "alias":"meltedcheese", "ratingdelta":-3, "rank":250, "activity":327, "score":453}, {"emblem":"<img src='https:\/\/github.com\/GalconElim\/elim_rankings\/raw\/master\/rank1.png' width=49 height=49 style='margin-top:-100%;margin-bottom:-100%;'\/>", "rating":899, "alias":"Yulia1984", "ratingdelta":"+1", "rank":251, "activity":606, "score":440}, {"emblem":"<img src='https:\/\/github.com\/GalconElim\/elim_rankings\/raw\/master\/rank1.png' width=49 height=49 style='margin-top:-100%;margin-bottom:-100%;'\/>", "rating":898, "alias":"mk5rabbit", "ratingdelta":"+2", "rank":252, "activity":697, "score":437}, {"emblem":"<img src='https:\/\/github.com\/GalconElim\/elim_rankings\/raw\/master\/rank1.png' width=49 height=49 style='margin-top:-100%;margin-bottom:-100%;'\/>", "rating":898, "alias":"MagicFox~931", "ratingdelta":0, "rank":253, "activity":108, "score":437}, {"emblem":"<img src='https:\/\/github.com\/GalconElim\/elim_rankings\/raw\/master\/rank1.png' width=49 height=49 style='margin-top:-100%;margin-bottom:-100%;'\/>", "rating":897, "alias":"GreenDeer~922", "ratingdelta":0, "rank":254, "activity":191, "score":436}, {"emblem":"<img src='https:\/\/github.com\/GalconElim\/elim_rankings\/raw\/master\/rank1.png' width=49 height=49 style='margin-top:-100%;margin-bottom:-100%;'\/>", "rating":887, "alias":"b3t1", "ratingdelta":0, "rank":255, "activity":404, "score":411}], "queryRecordCount":255, "totalRecordCount":255}